<!-- generated by jliftc at 2009-05-06 09:35:40 with arguments [-sigcp, /home/dhking/workspace/jif/analysis/jlift/bin/../sig-classes:/home/dhking/workspace/jif/analysis/jlift/bin/../lib/jifsig.jar, -declcons, -noex, Mastermind5.jl]-->
<constraint-set xmlns="http://openuri.org/constraint">
  <con>
    <lhs>
      <label name="LATTICE#0" isvar="false"/>
    </lhs>
    <rhs name="pc8" isvar="true" weight="1" procedure="1"/>
    <pos>Mastermind5.jl:11,11-38</pos>
    <because>final int{Alice: }[]{aliceGuess} aliceGuess</because>
    <becauseType>jif.ast.JifFormal_c</becauseType>
    <asString>{pc8} ==_{def} {}@Mastermind5.jl:11,11-38</asString>
  </con>
  <con>
    <lhs>
      <label name="pc8" isvar="true" weight="1" procedure="1"/>
    </lhs>
    <rhs name="local:returnArray" isvar="true" weight="1" procedure="1"/>
    <pos>Mastermind5.jl:14,23-34</pos>
    <because>null</because>
    <becauseType>polyglot.ast.NullLit_c</becauseType>
    <asString>{local:returnArray} == {pc8; Alice: ; _!: _}@Mastermind5.jl:14,23-34</asString>
  </con>
  <con>
    <lhs>
      <label name="LATTICE#1" isvar="false"/>
    </lhs>
    <rhs name="local:returnArray" isvar="true" weight="1" procedure="1"/>
    <pos>Mastermind5.jl:14,23-34</pos>
    <because>null</because>
    <becauseType>polyglot.ast.NullLit_c</becauseType>
    <asString>{local:returnArray} == {pc8; Alice: ; _!: _}@Mastermind5.jl:14,23-34</asString>
  </con>
  <con>
    <lhs>
      <label name="LATTICE#0" isvar="false"/>
    </lhs>
    <rhs name="NV9" isvar="true" weight="1" procedure="1" canDecl="true"/>
    <pos>Mastermind5.jl:14,37-41</pos>
    <because>null</because>
    <becauseType>polyglot.ast.NullLit_c</becauseType>
    <asString>{NV9} ==_{def} {*!: }@Mastermind5.jl:14,37-41</asString>
  </con>
  <con>
    <lhs>
      <label name="NV9" isvar="true" weight="1" procedure="1"/>
    </lhs>
    <rhs name="local:returnArray" isvar="true" weight="1" procedure="1"/>
    <pos>Mastermind5.jl:14,37-41</pos>
    <because>int{Alice: }[]{Alice: } returnArray = null;</because>
    <becauseType>jif.ast.JifLocalDecl_c</becauseType>
    <asString>{NV9} #lt= {local:returnArray}@Mastermind5.jl:14,37-41</asString>
  </con>
  <con>
    <lhs>
      <label name="NV9" isvar="true" weight="1" procedure="1"/>
    </lhs>
    <rhs name="NV10" isvar="true" weight="1" procedure="1" canDecl="true"/>
    <pos>Mastermind5.jl:14,23-34</pos>
    <because>int{Alice: }[]{Alice: } returnArray = null;</because>
    <becauseType>jif.ast.JifLocalDecl_c</becauseType>
    <asString>{NV10} ==_{def} {NV9}@Mastermind5.jl:14,23-34</asString>
  </con>
  <con>
    <lhs>
      <label name="LATTICE#1" isvar="false"/>
    </lhs>
    <rhs name="NV11" isvar="true" weight="1" procedure="1" canDecl="true"/>
    <pos>Mastermind5.jl:16,5-15</pos>
    <because>aliceGuess</because>
    <becauseType>polyglot.ast.Local_c</becauseType>
    <asString>{NV11} ==_{def} {Alice: }@Mastermind5.jl:16,5-15</asString>
  </con>
  <con>
    <lhs>
      <label name="NV11" isvar="true" weight="1" procedure="1"/>
    </lhs>
    <rhs name="field:length" isvar="true" weight="1" procedure="-1"/>
    <pos>Mastermind5.jl:16,5-22</pos>
    <because>aliceGuess.length</because>
    <becauseType>polyglot.ast.Field_c</becauseType>
    <asString>{field:length} ==_{def} {NV11}@Mastermind5.jl:16,5-22</asString>
  </con>
  <con>
    <lhs>
      <label name="field:length" isvar="true" weight="1" procedure="-1"/>
    </lhs>
    <rhs name="NV12" isvar="true" weight="1" procedure="1" canDecl="true"/>
    <pos>Mastermind5.jl:16,5-22</pos>
    <because>aliceGuess.length</because>
    <becauseType>polyglot.ast.Field_c</becauseType>
    <asString>{NV12} ==_{def} {field:length; NV11}@Mastermind5.jl:16,5-22</asString>
  </con>
  <con>
    <lhs>
      <label name="NV11" isvar="true" weight="1" procedure="1"/>
    </lhs>
    <rhs name="NV12" isvar="true" weight="1" procedure="1" canDecl="true"/>
    <pos>Mastermind5.jl:16,5-22</pos>
    <because>aliceGuess.length</because>
    <becauseType>polyglot.ast.Field_c</becauseType>
    <asString>{NV12} ==_{def} {field:length; NV11}@Mastermind5.jl:16,5-22</asString>
  </con>
  <con>
    <lhs>
      <label name="guess_apireceiver" isvar="true" weight="1" procedure="-1"/>
    </lhs>
    <rhs name="NV13" isvar="true" weight="1" procedure="1" canDecl="false"/>
    <pos>Mastermind5.jl:16,26-26</pos>
    <because>this</because>
    <becauseType>polyglot.ast.Special_c</becauseType>
    <asString>{NV13} ==_{def} {guess_apireceiver; pc8}@Mastermind5.jl:16,26-26</asString>
  </con>
  <con>
    <lhs>
      <label name="pc8" isvar="true" weight="1" procedure="1"/>
    </lhs>
    <rhs name="NV13" isvar="true" weight="1" procedure="1" canDecl="false"/>
    <pos>Mastermind5.jl:16,26-26</pos>
    <because>this</because>
    <becauseType>polyglot.ast.Special_c</becauseType>
    <asString>{NV13} ==_{def} {guess_apireceiver; pc8}@Mastermind5.jl:16,26-26</asString>
  </con>
  <con>
    <lhs>
      <label name="LATTICE#2" isvar="false"/>
    </lhs>
    <rhs name="field:code" isvar="true" weight="1" procedure="-1"/>
    <pos>Mastermind5.jl:16,26-30</pos>
    <because>this.code</because>
    <becauseType>polyglot.ast.Field_c</becauseType>
    <asString>{field:code} ==_{def} {Bob: }@Mastermind5.jl:16,26-30</asString>
  </con>
  <con>
    <lhs>
      <label name="field:code" isvar="true" weight="1" procedure="-1"/>
    </lhs>
    <rhs name="NV14" isvar="true" weight="1" procedure="1" canDecl="true"/>
    <pos>Mastermind5.jl:16,26-30</pos>
    <because>this.code</because>
    <becauseType>polyglot.ast.Field_c</becauseType>
    <asString>{NV14} ==_{def} {field:code; NV13}@Mastermind5.jl:16,26-30</asString>
  </con>
  <con>
    <lhs>
      <label name="NV13" isvar="true" weight="1" procedure="1"/>
    </lhs>
    <rhs name="NV14" isvar="true" weight="1" procedure="1" canDecl="true"/>
    <pos>Mastermind5.jl:16,26-30</pos>
    <because>this.code</because>
    <becauseType>polyglot.ast.Field_c</becauseType>
    <asString>{NV14} ==_{def} {field:code; NV13}@Mastermind5.jl:16,26-30</asString>
  </con>
  <con>
    <lhs>
      <label name="NV14" isvar="true" weight="1" procedure="1"/>
    </lhs>
    <rhs name="field:length:2" isvar="true" weight="1" procedure="-1"/>
    <pos>Mastermind5.jl:16,26-37</pos>
    <because>this.code.length</because>
    <becauseType>polyglot.ast.Field_c</becauseType>
    <asString>{field:length:2} ==_{def} {NV14}@Mastermind5.jl:16,26-37</asString>
  </con>
  <con>
    <lhs>
      <label name="field:length:2" isvar="true" weight="1" procedure="-1"/>
    </lhs>
    <rhs name="NV15" isvar="true" weight="1" procedure="1" canDecl="true"/>
    <pos>Mastermind5.jl:16,26-37</pos>
    <because>this.code.length</because>
    <becauseType>polyglot.ast.Field_c</becauseType>
    <asString>{NV15} ==_{def} {field:length:2; NV14}@Mastermind5.jl:16,26-37</asString>
  </con>
  <con>
    <lhs>
      <label name="NV14" isvar="true" weight="1" procedure="1"/>
    </lhs>
    <rhs name="NV15" isvar="true" weight="1" procedure="1" canDecl="true"/>
    <pos>Mastermind5.jl:16,26-37</pos>
    <because>this.code.length</because>
    <becauseType>polyglot.ast.Field_c</becauseType>
    <asString>{NV15} ==_{def} {field:length:2; NV14}@Mastermind5.jl:16,26-37</asString>
  </con>
  <con>
    <lhs>
      <label name="NV15" isvar="true" weight="1" procedure="1"/>
    </lhs>
    <rhs name="NV16" isvar="true" weight="1" procedure="1" canDecl="true"/>
    <pos>Mastermind5.jl:16,5-37</pos>
    <because>aliceGuess.length == this.code.length</because>
    <becauseType>jif.ast.JifBinary_c</becauseType>
    <asString>{NV16} ==_{def} {NV15; NV12}@Mastermind5.jl:16,5-37</asString>
  </con>
  <con>
    <lhs>
      <label name="NV12" isvar="true" weight="1" procedure="1"/>
    </lhs>
    <rhs name="NV16" isvar="true" weight="1" procedure="1" canDecl="true"/>
    <pos>Mastermind5.jl:16,5-37</pos>
    <because>aliceGuess.length == this.code.length</because>
    <becauseType>jif.ast.JifBinary_c</becauseType>
    <asString>{NV16} ==_{def} {NV15; NV12}@Mastermind5.jl:16,5-37</asString>
  </con>
  <con>
    <lhs>
      <label name="pc8" isvar="true" weight="1" procedure="1"/>
    </lhs>
    <rhs name="pc17" isvar="true" weight="1" procedure="1"/>
    <pos>Mastermind5.jl:16,1-46:2</pos>
    <because>aliceGuess</because>
    <becauseType>polyglot.ast.Local_c</becauseType>
    <asString>{pc17} ==_{def} {pc8; NV16}@Mastermind5.jl:16,1-46:2</asString>
  </con>
  <con>
    <lhs>
      <label name="NV16" isvar="true" weight="1" procedure="1"/>
    </lhs>
    <rhs name="pc17" isvar="true" weight="1" procedure="1"/>
    <pos>Mastermind5.jl:16,1-46:2</pos>
    <because>aliceGuess</because>
    <becauseType>polyglot.ast.Local_c</becauseType>
    <asString>{pc17} ==_{def} {pc8; NV16}@Mastermind5.jl:16,1-46:2</asString>
  </con>
  <con>
    <lhs>
      <label name="LATTICE#1" isvar="false"/>
    </lhs>
    <rhs name="NV18" isvar="true" weight="1" procedure="1" canDecl="true"/>
    <pos>Mastermind5.jl:19,27-37</pos>
    <because>aliceGuess</because>
    <becauseType>polyglot.ast.Local_c</becauseType>
    <asString>{NV18} ==_{def} {Alice: }@Mastermind5.jl:19,27-37</asString>
  </con>
  <con>
    <lhs>
      <label name="NV18" isvar="true" weight="1" procedure="1"/>
    </lhs>
    <rhs name="field:length" isvar="true" weight="1" procedure="-1"/>
    <pos>Mastermind5.jl:19,27-44</pos>
    <because>aliceGuess.length</because>
    <becauseType>polyglot.ast.Field_c</becauseType>
    <asString>{field:length} ==_{def} {NV18}@Mastermind5.jl:19,27-44</asString>
  </con>
  <con>
    <lhs>
      <label name="field:length" isvar="true" weight="1" procedure="-1"/>
    </lhs>
    <rhs name="NV19" isvar="true" weight="1" procedure="1" canDecl="true"/>
    <pos>Mastermind5.jl:19,27-44</pos>
    <because>aliceGuess.length</because>
    <becauseType>polyglot.ast.Field_c</becauseType>
    <asString>{NV19} ==_{def} {field:length; NV18}@Mastermind5.jl:19,27-44</asString>
  </con>
  <con>
    <lhs>
      <label name="NV18" isvar="true" weight="1" procedure="1"/>
    </lhs>
    <rhs name="NV19" isvar="true" weight="1" procedure="1" canDecl="true"/>
    <pos>Mastermind5.jl:19,27-44</pos>
    <because>aliceGuess.length</because>
    <becauseType>polyglot.ast.Field_c</becauseType>
    <asString>{NV19} ==_{def} {field:length; NV18}@Mastermind5.jl:19,27-44</asString>
  </con>
  <con>
    <lhs>
      <label name="NV19" isvar="true" weight="1" procedure="1"/>
    </lhs>
    <rhs name="NV20" isvar="true" weight="1" procedure="1" canDecl="true"/>
    <pos>Mastermind5.jl:19,19-45</pos>
    <because>new int[...]</because>
    <becauseType>polyglot.ast.NewArray_c</becauseType>
    <asString>{NV20} ==_{def} {NV19}@Mastermind5.jl:19,19-45</asString>
  </con>
  <con>
    <lhs>
      <label name="NV20" isvar="true" weight="1" procedure="1"/>
    </lhs>
    <rhs name="local:returnArray" isvar="true" weight="1" procedure="1"/>
    <pos>Mastermind5.jl:19,5-16</pos>
    <because>returnArray = new int[...]</because>
    <becauseType>polyglot.ast.LocalAssign_c</becauseType>
    <asString>{NV20} #lt= {local:returnArray}@Mastermind5.jl:19,5-16</asString>
  </con>
  <con>
    <lhs>
      <label name="pc17" isvar="true" weight="1" procedure="1"/>
    </lhs>
    <rhs name="local:returnArray" isvar="true" weight="1" procedure="1"/>
    <pos>Mastermind5.jl:19,5-16</pos>
    <because>returnArray = new int[...]</because>
    <becauseType>polyglot.ast.LocalAssign_c</becauseType>
    <asString>{pc17} #lt= {local:returnArray}@Mastermind5.jl:19,5-16</asString>
  </con>
  <con>
    <lhs>
      <label name="array_base" isvar="true" weight="1" procedure="-1"/>
    </lhs>
    <rhs name="LATTICE#1" isvar="false"/>
    <pos>Mastermind5.jl:19,5-45</pos>
    <because>returnArray = new int[...]</because>
    <becauseType>polyglot.ast.LocalAssign_c</becauseType>
    <asString>{array_base} #lt= {Alice: }@Mastermind5.jl:19,5-45</asString>
  </con>
  <con>
    <lhs>
      <label name="LATTICE#0" isvar="false"/>
    </lhs>
    <rhs name="NV21" isvar="true" weight="1" procedure="1" canDecl="true"/>
    <pos>Mastermind5.jl:20,13-14</pos>
    <because>0</because>
    <becauseType>polyglot.ast.IntLit_c</becauseType>
    <asString>{NV21} ==_{def} {*!: }@Mastermind5.jl:20,13-14</asString>
  </con>
  <con>
    <lhs>
      <label name="NV21" isvar="true" weight="1" procedure="1"/>
    </lhs>
    <rhs name="local:k" isvar="true" weight="1" procedure="1"/>
    <pos>Mastermind5.jl:20,13-14</pos>
    <because>int{local:k} k = 0;</because>
    <becauseType>jif.ast.JifLocalDecl_c</becauseType>
    <asString>{NV21} #lt= {local:k}@Mastermind5.jl:20,13-14</asString>
  </con>
  <con>
    <lhs>
      <label name="NV21" isvar="true" weight="1" procedure="1"/>
    </lhs>
    <rhs name="NV22" isvar="true" weight="1" procedure="1" canDecl="true"/>
    <pos>Mastermind5.jl:20,9-10</pos>
    <because>int{local:k} k = 0;</because>
    <becauseType>jif.ast.JifLocalDecl_c</becauseType>
    <asString>{NV22} ==_{def} {NV21}@Mastermind5.jl:20,9-10</asString>
  </con>
  <con>
    <lhs>
      <label name="LATTICE#0" isvar="false"/>
    </lhs>
    <rhs name="NV23" isvar="true" weight="1" procedure="1" canDecl="true"/>
    <pos>Mastermind5.jl:24,17-18</pos>
    <because>0</because>
    <becauseType>polyglot.ast.IntLit_c</becauseType>
    <asString>{NV23} ==_{def} {*!: }@Mastermind5.jl:24,17-18</asString>
  </con>
  <con>
    <lhs>
      <label name="NV23" isvar="true" weight="1" procedure="1"/>
    </lhs>
    <rhs name="local:j" isvar="true" weight="1" procedure="1"/>
    <pos>Mastermind5.jl:24,17-18</pos>
    <because>int{local:j} j = 0;</because>
    <becauseType>jif.ast.JifLocalDecl_c</becauseType>
    <asString>{NV23} #lt= {local:j}@Mastermind5.jl:24,17-18</asString>
  </con>
  <con>
    <lhs>
      <label name="NV23" isvar="true" weight="1" procedure="1"/>
    </lhs>
    <rhs name="NV24" isvar="true" weight="1" procedure="1" canDecl="true"/>
    <pos>Mastermind5.jl:24,13-14</pos>
    <because>int{local:j} j = 0;</because>
    <becauseType>jif.ast.JifLocalDecl_c</becauseType>
    <asString>{NV24} ==_{def} {NV23}@Mastermind5.jl:24,13-14</asString>
  </con>
  <con>
    <lhs>
      <label name="pc17" isvar="true" weight="1" procedure="1"/>
    </lhs>
    <rhs name="pc25" isvar="true" weight="1" procedure="1"/>
    <pos>Mastermind5.jl:24,5-36</pos>
    <because>j</because>
    <becauseType>polyglot.ast.Local_c</becauseType>
    <asString>{pc25} ==_{def} {pc17; for}@Mastermind5.jl:24,5-36</asString>
  </con>
  <con>
    <lhs>
      <label name="for" isvar="true" weight="1" procedure="1"/>
    </lhs>
    <rhs name="pc25" isvar="true" weight="1" procedure="1"/>
    <pos>Mastermind5.jl:24,5-36</pos>
    <because>j</because>
    <becauseType>polyglot.ast.Local_c</becauseType>
    <asString>{pc25} ==_{def} {pc17; for}@Mastermind5.jl:24,5-36</asString>
  </con>
  <con>
    <lhs>
      <label name="local:j" isvar="true" weight="1" procedure="1"/>
    </lhs>
    <rhs name="NV26" isvar="true" weight="1" procedure="1" canDecl="true"/>
    <pos>Mastermind5.jl:24,20-21</pos>
    <because>j</because>
    <becauseType>polyglot.ast.Local_c</becauseType>
    <asString>{NV26} ==_{def} {local:j}@Mastermind5.jl:24,20-21</asString>
  </con>
  <con>
    <lhs>
      <label name="guess_apireceiver" isvar="true" weight="1" procedure="-1"/>
    </lhs>
    <rhs name="NV27" isvar="true" weight="1" procedure="1" canDecl="false"/>
    <pos>Mastermind5.jl:24,24-24</pos>
    <because>this</because>
    <becauseType>polyglot.ast.Special_c</becauseType>
    <asString>{NV27} ==_{def} {guess_apireceiver; pc25}@Mastermind5.jl:24,24-24</asString>
  </con>
  <con>
    <lhs>
      <label name="pc25" isvar="true" weight="1" procedure="1"/>
    </lhs>
    <rhs name="NV27" isvar="true" weight="1" procedure="1" canDecl="false"/>
    <pos>Mastermind5.jl:24,24-24</pos>
    <because>this</because>
    <becauseType>polyglot.ast.Special_c</becauseType>
    <asString>{NV27} ==_{def} {guess_apireceiver; pc25}@Mastermind5.jl:24,24-24</asString>
  </con>
  <con>
    <lhs>
      <label name="LATTICE#2" isvar="false"/>
    </lhs>
    <rhs name="field:code" isvar="true" weight="1" procedure="-1"/>
    <pos>Mastermind5.jl:24,24-28</pos>
    <because>this.code</because>
    <becauseType>polyglot.ast.Field_c</becauseType>
    <asString>{field:code} ==_{def} {Bob: }@Mastermind5.jl:24,24-28</asString>
  </con>
  <con>
    <lhs>
      <label name="field:code" isvar="true" weight="1" procedure="-1"/>
    </lhs>
    <rhs name="NV28" isvar="true" weight="1" procedure="1" canDecl="true"/>
    <pos>Mastermind5.jl:24,24-28</pos>
    <because>this.code</because>
    <becauseType>polyglot.ast.Field_c</becauseType>
    <asString>{NV28} ==_{def} {field:code; NV27}@Mastermind5.jl:24,24-28</asString>
  </con>
  <con>
    <lhs>
      <label name="NV27" isvar="true" weight="1" procedure="1"/>
    </lhs>
    <rhs name="NV28" isvar="true" weight="1" procedure="1" canDecl="true"/>
    <pos>Mastermind5.jl:24,24-28</pos>
    <because>this.code</because>
    <becauseType>polyglot.ast.Field_c</becauseType>
    <asString>{NV28} ==_{def} {field:code; NV27}@Mastermind5.jl:24,24-28</asString>
  </con>
  <con>
    <lhs>
      <label name="NV28" isvar="true" weight="1" procedure="1"/>
    </lhs>
    <rhs name="field:length:2" isvar="true" weight="1" procedure="-1"/>
    <pos>Mastermind5.jl:24,24-35</pos>
    <because>this.code.length</because>
    <becauseType>polyglot.ast.Field_c</becauseType>
    <asString>{field:length:2} ==_{def} {NV28}@Mastermind5.jl:24,24-35</asString>
  </con>
  <con>
    <lhs>
      <label name="field:length:2" isvar="true" weight="1" procedure="-1"/>
    </lhs>
    <rhs name="NV29" isvar="true" weight="1" procedure="1" canDecl="true"/>
    <pos>Mastermind5.jl:24,24-35</pos>
    <because>this.code.length</because>
    <becauseType>polyglot.ast.Field_c</becauseType>
    <asString>{NV29} ==_{def} {field:length:2; NV28}@Mastermind5.jl:24,24-35</asString>
  </con>
  <con>
    <lhs>
      <label name="NV28" isvar="true" weight="1" procedure="1"/>
    </lhs>
    <rhs name="NV29" isvar="true" weight="1" procedure="1" canDecl="true"/>
    <pos>Mastermind5.jl:24,24-35</pos>
    <because>this.code.length</because>
    <becauseType>polyglot.ast.Field_c</becauseType>
    <asString>{NV29} ==_{def} {field:length:2; NV28}@Mastermind5.jl:24,24-35</asString>
  </con>
  <con>
    <lhs>
      <label name="NV29" isvar="true" weight="1" procedure="1"/>
    </lhs>
    <rhs name="NV30" isvar="true" weight="1" procedure="1" canDecl="true"/>
    <pos>Mastermind5.jl:24,20-35</pos>
    <because>j #lt this.code.length</because>
    <becauseType>jif.ast.JifBinary_c</becauseType>
    <asString>{NV30} ==_{def} {NV29; NV26}@Mastermind5.jl:24,20-35</asString>
  </con>
  <con>
    <lhs>
      <label name="NV26" isvar="true" weight="1" procedure="1"/>
    </lhs>
    <rhs name="NV30" isvar="true" weight="1" procedure="1" canDecl="true"/>
    <pos>Mastermind5.jl:24,20-35</pos>
    <because>j #lt this.code.length</because>
    <becauseType>jif.ast.JifBinary_c</becauseType>
    <asString>{NV30} ==_{def} {NV29; NV26}@Mastermind5.jl:24,20-35</asString>
  </con>
  <con>
    <lhs>
      <label name="pc25" isvar="true" weight="1" procedure="1"/>
    </lhs>
    <rhs name="pc31" isvar="true" weight="1" procedure="1"/>
    <pos>Mastermind5.jl:24,5-36</pos>
    <because>1</because>
    <becauseType>polyglot.ast.IntLit_c</becauseType>
    <asString>{pc31} ==_{def} {pc25; NV30}@Mastermind5.jl:24,5-36</asString>
  </con>
  <con>
    <lhs>
      <label name="NV30" isvar="true" weight="1" procedure="1"/>
    </lhs>
    <rhs name="pc31" isvar="true" weight="1" procedure="1"/>
    <pos>Mastermind5.jl:24,5-36</pos>
    <because>1</because>
    <becauseType>polyglot.ast.IntLit_c</becauseType>
    <asString>{pc31} ==_{def} {pc25; NV30}@Mastermind5.jl:24,5-36</asString>
  </con>
  <con>
    <lhs>
      <label name="LATTICE#0" isvar="false"/>
    </lhs>
    <rhs name="NV32" isvar="true" weight="1" procedure="1" canDecl="true"/>
    <pos>Mastermind5.jl:26,21-22</pos>
    <because>1</because>
    <becauseType>polyglot.ast.IntLit_c</becauseType>
    <asString>{NV32} ==_{def} {*!: }@Mastermind5.jl:26,21-22</asString>
  </con>
  <con>
    <lhs>
      <label name="NV32" isvar="true" weight="1" procedure="1"/>
    </lhs>
    <rhs name="local:guessResult" isvar="true" weight="1" procedure="1"/>
    <pos>Mastermind5.jl:26,20-22</pos>
    <because>int{local:guessResult} guessResult = -1;</because>
    <becauseType>jif.ast.JifLocalDecl_c</becauseType>
    <asString>{NV32} #lt= {local:guessResult}@Mastermind5.jl:26,20-22</asString>
  </con>
  <con>
    <lhs>
      <label name="NV32" isvar="true" weight="1" procedure="1"/>
    </lhs>
    <rhs name="NV33" isvar="true" weight="1" procedure="1" canDecl="true"/>
    <pos>Mastermind5.jl:26,6-17</pos>
    <because>int{local:guessResult} guessResult = -1;</because>
    <becauseType>jif.ast.JifLocalDecl_c</becauseType>
    <asString>{NV33} ==_{def} {NV32}@Mastermind5.jl:26,6-17</asString>
  </con>
  <con>
    <lhs>
      <label name="LATTICE#1" isvar="false"/>
    </lhs>
    <rhs name="NV34" isvar="true" weight="1" procedure="1" canDecl="true"/>
    <pos>Mastermind5.jl:27,6-16</pos>
    <because>aliceGuess</because>
    <becauseType>polyglot.ast.Local_c</becauseType>
    <asString>{NV34} ==_{def} {Alice: }@Mastermind5.jl:27,6-16</asString>
  </con>
  <con>
    <lhs>
      <label name="local:j" isvar="true" weight="1" procedure="1"/>
    </lhs>
    <rhs name="NV35" isvar="true" weight="1" procedure="1" canDecl="true"/>
    <pos>Mastermind5.jl:27,17-18</pos>
    <because>j</because>
    <becauseType>polyglot.ast.Local_c</becauseType>
    <asString>{NV35} ==_{def} {local:j}@Mastermind5.jl:27,17-18</asString>
  </con>
  <con>
    <lhs>
      <label name="NV35" isvar="true" weight="1" procedure="1"/>
    </lhs>
    <rhs name="NV36" isvar="true" weight="1" procedure="1" canDecl="true"/>
    <pos>Mastermind5.jl:27,6-16</pos>
    <because>aliceGuess[j]</because>
    <becauseType>polyglot.ast.ArrayAccess_c</becauseType>
    <asString>{NV36} ==_{def} {NV35; NV34}@Mastermind5.jl:27,6-16</asString>
  </con>
  <con>
    <lhs>
      <label name="NV34" isvar="true" weight="1" procedure="1"/>
    </lhs>
    <rhs name="NV36" isvar="true" weight="1" procedure="1" canDecl="true"/>
    <pos>Mastermind5.jl:27,6-16</pos>
    <because>aliceGuess[j]</because>
    <becauseType>polyglot.ast.ArrayAccess_c</becauseType>
    <asString>{NV36} ==_{def} {NV35; NV34}@Mastermind5.jl:27,6-16</asString>
  </con>
  <con>
    <lhs>
      <label name="LATTICE#1" isvar="false"/>
    </lhs>
    <rhs name="NV37" isvar="true" weight="1" procedure="1" canDecl="true"/>
    <pos>Mastermind5.jl:27,6-16</pos>
    <because>aliceGuess[j]</because>
    <becauseType>polyglot.ast.ArrayAccess_c</becauseType>
    <asString>{NV37} ==_{def} {Alice: ; _!: _; NV36}@Mastermind5.jl:27,6-16</asString>
  </con>
  <con>
    <lhs>
      <label name="NV36" isvar="true" weight="1" procedure="1"/>
    </lhs>
    <rhs name="NV37" isvar="true" weight="1" procedure="1" canDecl="true"/>
    <pos>Mastermind5.jl:27,6-16</pos>
    <because>aliceGuess[j]</because>
    <becauseType>polyglot.ast.ArrayAccess_c</becauseType>
    <asString>{NV37} ==_{def} {Alice: ; _!: _; NV36}@Mastermind5.jl:27,6-16</asString>
  </con>
  <con>
    <lhs>
      <label name="guess_apireceiver" isvar="true" weight="1" procedure="-1"/>
    </lhs>
    <rhs name="NV38" isvar="true" weight="1" procedure="1" canDecl="false"/>
    <pos>Mastermind5.jl:27,23-23</pos>
    <because>this</because>
    <becauseType>polyglot.ast.Special_c</becauseType>
    <asString>{NV38} ==_{def} {guess_apireceiver; pc31}@Mastermind5.jl:27,23-23</asString>
  </con>
  <con>
    <lhs>
      <label name="pc31" isvar="true" weight="1" procedure="1"/>
    </lhs>
    <rhs name="NV38" isvar="true" weight="1" procedure="1" canDecl="false"/>
    <pos>Mastermind5.jl:27,23-23</pos>
    <because>this</because>
    <becauseType>polyglot.ast.Special_c</becauseType>
    <asString>{NV38} ==_{def} {guess_apireceiver; pc31}@Mastermind5.jl:27,23-23</asString>
  </con>
  <con>
    <lhs>
      <label name="LATTICE#2" isvar="false"/>
    </lhs>
    <rhs name="field:code" isvar="true" weight="1" procedure="-1"/>
    <pos>Mastermind5.jl:27,23-27</pos>
    <because>this.code</because>
    <becauseType>polyglot.ast.Field_c</becauseType>
    <asString>{field:code} ==_{def} {Bob: }@Mastermind5.jl:27,23-27</asString>
  </con>
  <con>
    <lhs>
      <label name="field:code" isvar="true" weight="1" procedure="-1"/>
    </lhs>
    <rhs name="NV39" isvar="true" weight="1" procedure="1" canDecl="true"/>
    <pos>Mastermind5.jl:27,23-27</pos>
    <because>this.code</because>
    <becauseType>polyglot.ast.Field_c</becauseType>
    <asString>{NV39} ==_{def} {field:code; NV38}@Mastermind5.jl:27,23-27</asString>
  </con>
  <con>
    <lhs>
      <label name="NV38" isvar="true" weight="1" procedure="1"/>
    </lhs>
    <rhs name="NV39" isvar="true" weight="1" procedure="1" canDecl="true"/>
    <pos>Mastermind5.jl:27,23-27</pos>
    <because>this.code</because>
    <becauseType>polyglot.ast.Field_c</becauseType>
    <asString>{NV39} ==_{def} {field:code; NV38}@Mastermind5.jl:27,23-27</asString>
  </con>
  <con>
    <lhs>
      <label name="local:j" isvar="true" weight="1" procedure="1"/>
    </lhs>
    <rhs name="NV40" isvar="true" weight="1" procedure="1" canDecl="true"/>
    <pos>Mastermind5.jl:27,28-29</pos>
    <because>j</because>
    <becauseType>polyglot.ast.Local_c</becauseType>
    <asString>{NV40} ==_{def} {local:j}@Mastermind5.jl:27,28-29</asString>
  </con>
  <con>
    <lhs>
      <label name="NV40" isvar="true" weight="1" procedure="1"/>
    </lhs>
    <rhs name="NV41" isvar="true" weight="1" procedure="1" canDecl="true"/>
    <pos>Mastermind5.jl:27,23-27</pos>
    <because>this.code[j]</because>
    <becauseType>polyglot.ast.ArrayAccess_c</becauseType>
    <asString>{NV41} ==_{def} {NV40; NV39}@Mastermind5.jl:27,23-27</asString>
  </con>
  <con>
    <lhs>
      <label name="NV39" isvar="true" weight="1" procedure="1"/>
    </lhs>
    <rhs name="NV41" isvar="true" weight="1" procedure="1" canDecl="true"/>
    <pos>Mastermind5.jl:27,23-27</pos>
    <because>this.code[j]</because>
    <becauseType>polyglot.ast.ArrayAccess_c</becauseType>
    <asString>{NV41} ==_{def} {NV40; NV39}@Mastermind5.jl:27,23-27</asString>
  </con>
  <con>
    <lhs>
      <label name="LATTICE#2" isvar="false"/>
    </lhs>
    <rhs name="NV42" isvar="true" weight="1" procedure="1" canDecl="true"/>
    <pos>Mastermind5.jl:27,23-27</pos>
    <because>this.code[j]</because>
    <becauseType>polyglot.ast.ArrayAccess_c</becauseType>
    <asString>{NV42} ==_{def} {Bob: ; _!: _; NV41}@Mastermind5.jl:27,23-27</asString>
  </con>
  <con>
    <lhs>
      <label name="NV41" isvar="true" weight="1" procedure="1"/>
    </lhs>
    <rhs name="NV42" isvar="true" weight="1" procedure="1" canDecl="true"/>
    <pos>Mastermind5.jl:27,23-27</pos>
    <because>this.code[j]</because>
    <becauseType>polyglot.ast.ArrayAccess_c</becauseType>
    <asString>{NV42} ==_{def} {Bob: ; _!: _; NV41}@Mastermind5.jl:27,23-27</asString>
  </con>
  <con>
    <lhs>
      <label name="NV42" isvar="true" weight="1" procedure="1"/>
    </lhs>
    <rhs name="NV43" isvar="true" weight="1" procedure="1" canDecl="true"/>
    <pos>Mastermind5.jl:27,6-27</pos>
    <because>aliceGuess[j] == this.code[j]</because>
    <becauseType>jif.ast.JifBinary_c</becauseType>
    <asString>{NV43} ==_{def} {NV42; NV37}@Mastermind5.jl:27,6-27</asString>
  </con>
  <con>
    <lhs>
      <label name="NV37" isvar="true" weight="1" procedure="1"/>
    </lhs>
    <rhs name="NV43" isvar="true" weight="1" procedure="1" canDecl="true"/>
    <pos>Mastermind5.jl:27,6-27</pos>
    <because>aliceGuess[j] == this.code[j]</because>
    <becauseType>jif.ast.JifBinary_c</becauseType>
    <asString>{NV43} ==_{def} {NV42; NV37}@Mastermind5.jl:27,6-27</asString>
  </con>
  <con>
    <lhs>
      <label name="pc31" isvar="true" weight="1" procedure="1"/>
    </lhs>
    <rhs name="pc44" isvar="true" weight="1" procedure="1"/>
    <pos>Mastermind5.jl:27,2-39:3</pos>
    <because>usedToIndicateCorrectColor</because>
    <becauseType>polyglot.ast.Local_c</becauseType>
    <asString>{pc44} ==_{def} {pc31; NV43}@Mastermind5.jl:27,2-39:3</asString>
  </con>
  <con>
    <lhs>
      <label name="NV43" isvar="true" weight="1" procedure="1"/>
    </lhs>
    <rhs name="pc44" isvar="true" weight="1" procedure="1"/>
    <pos>Mastermind5.jl:27,2-39:3</pos>
    <because>usedToIndicateCorrectColor</because>
    <becauseType>polyglot.ast.Local_c</becauseType>
    <asString>{pc44} ==_{def} {pc31; NV43}@Mastermind5.jl:27,2-39:3</asString>
  </con>
  <con>
    <lhs>
      <label name="local:usedToIndicateCorrectColor" isvar="true" weight="1" procedure="1"/>
    </lhs>
    <rhs name="NV45" isvar="true" weight="1" procedure="1" canDecl="true"/>
    <pos>Mastermind5.jl:28,6-32</pos>
    <because>usedToIndicateCorrectColor</because>
    <becauseType>polyglot.ast.Local_c</becauseType>
    <asString>{NV45} ==_{def} {local:usedToIndicateCorrectColor}@Mastermind5.jl:28,6-32</asString>
  </con>
  <con>
    <lhs>
      <label name="local:j" isvar="true" weight="1" procedure="1"/>
    </lhs>
    <rhs name="NV46" isvar="true" weight="1" procedure="1" canDecl="true"/>
    <pos>Mastermind5.jl:28,33-34</pos>
    <because>j</because>
    <becauseType>polyglot.ast.Local_c</becauseType>
    <asString>{NV46} ==_{def} {local:j}@Mastermind5.jl:28,33-34</asString>
  </con>
  <con>
    <lhs>
      <label name="NV46" isvar="true" weight="1" procedure="1"/>
    </lhs>
    <rhs name="NV47" isvar="true" weight="1" procedure="1" canDecl="true"/>
    <pos>Mastermind5.jl:28,6-39</pos>
    <because>1</because>
    <becauseType>polyglot.ast.IntLit_c</becauseType>
    <asString>{NV47} ==_{def} {NV46; NV45}@Mastermind5.jl:28,6-39</asString>
  </con>
  <con>
    <lhs>
      <label name="NV45" isvar="true" weight="1" procedure="1"/>
    </lhs>
    <rhs name="NV47" isvar="true" weight="1" procedure="1" canDecl="true"/>
    <pos>Mastermind5.jl:28,6-39</pos>
    <because>1</because>
    <becauseType>polyglot.ast.IntLit_c</becauseType>
    <asString>{NV47} ==_{def} {NV46; NV45}@Mastermind5.jl:28,6-39</asString>
  </con>
  <con>
    <lhs>
      <label name="LATTICE#0" isvar="false"/>
    </lhs>
    <rhs name="NV48" isvar="true" weight="1" procedure="1" canDecl="true"/>
    <pos>Mastermind5.jl:28,38-39</pos>
    <because>1</because>
    <becauseType>polyglot.ast.IntLit_c</becauseType>
    <asString>{NV48} ==_{def} {*!: }@Mastermind5.jl:28,38-39</asString>
  </con>
  <con>
    <lhs>
      <label name="NV48" isvar="true" weight="1" procedure="1"/>
    </lhs>
    <rhs name="NV49" isvar="true" weight="1" procedure="1" canDecl="true"/>
    <pos>Mastermind5.jl:28,6-39</pos>
    <because>usedToIndicateCorrectColor[j] = 1</because>
    <becauseType>jif.ast.JifArrayAccessAssign_c</becauseType>
    <asString>{NV49} ==_{def} {NV48; NV47}@Mastermind5.jl:28,6-39</asString>
  </con>
  <con>
    <lhs>
      <label name="NV47" isvar="true" weight="1" procedure="1"/>
    </lhs>
    <rhs name="NV49" isvar="true" weight="1" procedure="1" canDecl="true"/>
    <pos>Mastermind5.jl:28,6-39</pos>
    <because>usedToIndicateCorrectColor[j] = 1</because>
    <becauseType>jif.ast.JifArrayAccessAssign_c</becauseType>
    <asString>{NV49} ==_{def} {NV48; NV47}@Mastermind5.jl:28,6-39</asString>
  </con>
  <con>
    <lhs>
      <label name="NV48" isvar="true" weight="1" procedure="1"/>
    </lhs>
    <rhs name="NV6" isvar="true" weight="1" procedure="1"/>
    <pos>Mastermind5.jl:28,6-32</pos>
    <because>usedToIndicateCorrectColor[j] = 1</because>
    <becauseType>jif.ast.JifArrayAccessAssign_c</becauseType>
    <asString>{NV48; pc44} #lt= {NV6}@Mastermind5.jl:28,6-32</asString>
  </con>
  <con>
    <lhs>
      <label name="pc44" isvar="true" weight="1" procedure="1"/>
    </lhs>
    <rhs name="NV6" isvar="true" weight="1" procedure="1"/>
    <pos>Mastermind5.jl:28,6-32</pos>
    <because>usedToIndicateCorrectColor[j] = 1</because>
    <becauseType>jif.ast.JifArrayAccessAssign_c</becauseType>
    <asString>{NV48; pc44} #lt= {NV6}@Mastermind5.jl:28,6-32</asString>
  </con>
  <con>
    <lhs>
      <label name="pc44" isvar="true" weight="1" procedure="1"/>
    </lhs>
    <rhs name="NV6" isvar="true" weight="1" procedure="1"/>
    <pos>Mastermind5.jl:28,6-32</pos>
    <because>usedToIndicateCorrectColor[j] = 1</because>
    <becauseType>jif.ast.JifArrayAccessAssign_c</becauseType>
    <asString>{pc44} #lt= {NV6}@Mastermind5.jl:28,6-32</asString>
  </con>
  <con>
    <lhs>
      <label name="LATTICE#0" isvar="false"/>
    </lhs>
    <rhs name="NV6" isvar="true" weight="1" procedure="1"/>
    <pos>Mastermind5.jl:28,6-32</pos>
    <because>usedToIndicateCorrectColor[j] = 1</because>
    <becauseType>jif.ast.JifArrayAccessAssign_c</becauseType>
    <asString>{} #lt= {NV6}@Mastermind5.jl:28,6-32</asString>
  </con>
  <con>
    <lhs>
      <label name="guess_apireceiver" isvar="true" weight="1" procedure="-1"/>
    </lhs>
    <rhs name="NV50" isvar="true" weight="1" procedure="1" canDecl="false"/>
    <pos>Mastermind5.jl:29,20-20</pos>
    <because>this</because>
    <becauseType>polyglot.ast.Special_c</becauseType>
    <asString>{NV50} ==_{def} {guess_apireceiver; pc44}@Mastermind5.jl:29,20-20</asString>
  </con>
  <con>
    <lhs>
      <label name="pc44" isvar="true" weight="1" procedure="1"/>
    </lhs>
    <rhs name="NV50" isvar="true" weight="1" procedure="1" canDecl="false"/>
    <pos>Mastermind5.jl:29,20-20</pos>
    <because>this</because>
    <becauseType>polyglot.ast.Special_c</becauseType>
    <asString>{NV50} ==_{def} {guess_apireceiver; pc44}@Mastermind5.jl:29,20-20</asString>
  </con>
  <con>
    <lhs>
      <label name="inst(CORRECT_COLOR_AND_POSITION)" isvar="true" weight="1" procedure="-1"/>
    </lhs>
    <rhs name="field:CORRECT_COLOR_AND_POSITION" isvar="true" weight="1" procedure="-1"/>
    <pos>Mastermind5.jl:29,20-46</pos>
    <because>this.CORRECT_COLOR_AND_POSITION</because>
    <becauseType>polyglot.ast.Field_c</becauseType>
    <asString>{field:CORRECT_COLOR_AND_POSITION} ==_{def} {inst(CORRECT_COLOR_AND_POSITION)}@Mastermind5.jl:29,20-46</asString>
  </con>
  <con>
    <lhs>
      <label name="field:CORRECT_COLOR_AND_POSITION" isvar="true" weight="1" procedure="-1"/>
    </lhs>
    <rhs name="NV51" isvar="true" weight="1" procedure="1" canDecl="true"/>
    <pos>Mastermind5.jl:29,20-46</pos>
    <because>this.CORRECT_COLOR_AND_POSITION</because>
    <becauseType>polyglot.ast.Field_c</becauseType>
    <asString>{NV51} ==_{def} {field:CORRECT_COLOR_AND_POSITION; NV50}@Mastermind5.jl:29,20-46</asString>
  </con>
  <con>
    <lhs>
      <label name="NV50" isvar="true" weight="1" procedure="1"/>
    </lhs>
    <rhs name="NV51" isvar="true" weight="1" procedure="1" canDecl="true"/>
    <pos>Mastermind5.jl:29,20-46</pos>
    <because>this.CORRECT_COLOR_AND_POSITION</because>
    <becauseType>polyglot.ast.Field_c</becauseType>
    <asString>{NV51} ==_{def} {field:CORRECT_COLOR_AND_POSITION; NV50}@Mastermind5.jl:29,20-46</asString>
  </con>
  <con>
    <lhs>
      <label name="NV51" isvar="true" weight="1" procedure="1"/>
    </lhs>
    <rhs name="local:guessResult" isvar="true" weight="1" procedure="1"/>
    <pos>Mastermind5.jl:29,6-17</pos>
    <because>guessResult = this.CORRECT_COLOR_AND_POSITION</because>
    <becauseType>polyglot.ast.LocalAssign_c</becauseType>
    <asString>{NV51} #lt= {local:guessResult}@Mastermind5.jl:29,6-17</asString>
  </con>
  <con>
    <lhs>
      <label name="pc44" isvar="true" weight="1" procedure="1"/>
    </lhs>
    <rhs name="local:guessResult" isvar="true" weight="1" procedure="1"/>
    <pos>Mastermind5.jl:29,6-17</pos>
    <because>guessResult = this.CORRECT_COLOR_AND_POSITION</because>
    <becauseType>polyglot.ast.LocalAssign_c</becauseType>
    <asString>{pc44} #lt= {local:guessResult}@Mastermind5.jl:29,6-17</asString>
  </con>
  <con>
    <lhs>
      <label name="pc31" isvar="true" weight="1" procedure="1"/>
    </lhs>
    <rhs name="pc52" isvar="true" weight="1" procedure="1"/>
    <pos>Mastermind5.jl:27,2-39:3</pos>
    <because>0</because>
    <becauseType>polyglot.ast.IntLit_c</becauseType>
    <asString>{pc52} ==_{def} {pc31; NV43}@Mastermind5.jl:27,2-39:3</asString>
  </con>
  <con>
    <lhs>
      <label name="NV43" isvar="true" weight="1" procedure="1"/>
    </lhs>
    <rhs name="pc52" isvar="true" weight="1" procedure="1"/>
    <pos>Mastermind5.jl:27,2-39:3</pos>
    <because>0</because>
    <becauseType>polyglot.ast.IntLit_c</becauseType>
    <asString>{pc52} ==_{def} {pc31; NV43}@Mastermind5.jl:27,2-39:3</asString>
  </con>
  <con>
    <lhs>
      <label name="LATTICE#0" isvar="false"/>
    </lhs>
    <rhs name="NV53" isvar="true" weight="1" procedure="1" canDecl="true"/>
    <pos>Mastermind5.jl:32,18-19</pos>
    <because>0</because>
    <becauseType>polyglot.ast.IntLit_c</becauseType>
    <asString>{NV53} ==_{def} {*!: }@Mastermind5.jl:32,18-19</asString>
  </con>
  <con>
    <lhs>
      <label name="NV53" isvar="true" weight="1" procedure="1"/>
    </lhs>
    <rhs name="local:i" isvar="true" weight="1" procedure="1"/>
    <pos>Mastermind5.jl:32,18-19</pos>
    <because>int{local:i} i = 0;</because>
    <becauseType>jif.ast.JifLocalDecl_c</becauseType>
    <asString>{NV53} #lt= {local:i}@Mastermind5.jl:32,18-19</asString>
  </con>
  <con>
    <lhs>
      <label name="NV53" isvar="true" weight="1" procedure="1"/>
    </lhs>
    <rhs name="NV54" isvar="true" weight="1" procedure="1" canDecl="true"/>
    <pos>Mastermind5.jl:32,14-15</pos>
    <because>int{local:i} i = 0;</because>
    <becauseType>jif.ast.JifLocalDecl_c</becauseType>
    <asString>{NV54} ==_{def} {NV53}@Mastermind5.jl:32,14-15</asString>
  </con>
  <con>
    <lhs>
      <label name="pc52" isvar="true" weight="1" procedure="1"/>
    </lhs>
    <rhs name="pc55" isvar="true" weight="1" procedure="1"/>
    <pos>Mastermind5.jl:32,6-37</pos>
    <because>i</because>
    <becauseType>polyglot.ast.Local_c</becauseType>
    <asString>{pc55} ==_{def} {pc52; for:2}@Mastermind5.jl:32,6-37</asString>
  </con>
  <con>
    <lhs>
      <label name="for:2" isvar="true" weight="1" procedure="1"/>
    </lhs>
    <rhs name="pc55" isvar="true" weight="1" procedure="1"/>
    <pos>Mastermind5.jl:32,6-37</pos>
    <because>i</because>
    <becauseType>polyglot.ast.Local_c</becauseType>
    <asString>{pc55} ==_{def} {pc52; for:2}@Mastermind5.jl:32,6-37</asString>
  </con>
  <con>
    <lhs>
      <label name="local:i" isvar="true" weight="1" procedure="1"/>
    </lhs>
    <rhs name="NV56" isvar="true" weight="1" procedure="1" canDecl="true"/>
    <pos>Mastermind5.jl:32,21-22</pos>
    <because>i</because>
    <becauseType>polyglot.ast.Local_c</becauseType>
    <asString>{NV56} ==_{def} {local:i}@Mastermind5.jl:32,21-22</asString>
  </con>
  <con>
    <lhs>
      <label name="guess_apireceiver" isvar="true" weight="1" procedure="-1"/>
    </lhs>
    <rhs name="NV57" isvar="true" weight="1" procedure="1" canDecl="false"/>
    <pos>Mastermind5.jl:32,25-25</pos>
    <because>this</because>
    <becauseType>polyglot.ast.Special_c</becauseType>
    <asString>{NV57} ==_{def} {guess_apireceiver; pc55}@Mastermind5.jl:32,25-25</asString>
  </con>
  <con>
    <lhs>
      <label name="pc55" isvar="true" weight="1" procedure="1"/>
    </lhs>
    <rhs name="NV57" isvar="true" weight="1" procedure="1" canDecl="false"/>
    <pos>Mastermind5.jl:32,25-25</pos>
    <because>this</because>
    <becauseType>polyglot.ast.Special_c</becauseType>
    <asString>{NV57} ==_{def} {guess_apireceiver; pc55}@Mastermind5.jl:32,25-25</asString>
  </con>
  <con>
    <lhs>
      <label name="LATTICE#2" isvar="false"/>
    </lhs>
    <rhs name="field:code" isvar="true" weight="1" procedure="-1"/>
    <pos>Mastermind5.jl:32,25-29</pos>
    <because>this.code</because>
    <becauseType>polyglot.ast.Field_c</becauseType>
    <asString>{field:code} ==_{def} {Bob: }@Mastermind5.jl:32,25-29</asString>
  </con>
  <con>
    <lhs>
      <label name="field:code" isvar="true" weight="1" procedure="-1"/>
    </lhs>
    <rhs name="NV58" isvar="true" weight="1" procedure="1" canDecl="true"/>
    <pos>Mastermind5.jl:32,25-29</pos>
    <because>this.code</because>
    <becauseType>polyglot.ast.Field_c</becauseType>
    <asString>{NV58} ==_{def} {field:code; NV57}@Mastermind5.jl:32,25-29</asString>
  </con>
  <con>
    <lhs>
      <label name="NV57" isvar="true" weight="1" procedure="1"/>
    </lhs>
    <rhs name="NV58" isvar="true" weight="1" procedure="1" canDecl="true"/>
    <pos>Mastermind5.jl:32,25-29</pos>
    <because>this.code</because>
    <becauseType>polyglot.ast.Field_c</becauseType>
    <asString>{NV58} ==_{def} {field:code; NV57}@Mastermind5.jl:32,25-29</asString>
  </con>
  <con>
    <lhs>
      <label name="NV58" isvar="true" weight="1" procedure="1"/>
    </lhs>
    <rhs name="field:length:2" isvar="true" weight="1" procedure="-1"/>
    <pos>Mastermind5.jl:32,25-36</pos>
    <because>this.code.length</because>
    <becauseType>polyglot.ast.Field_c</becauseType>
    <asString>{field:length:2} ==_{def} {NV58}@Mastermind5.jl:32,25-36</asString>
  </con>
  <con>
    <lhs>
      <label name="field:length:2" isvar="true" weight="1" procedure="-1"/>
    </lhs>
    <rhs name="NV59" isvar="true" weight="1" procedure="1" canDecl="true"/>
    <pos>Mastermind5.jl:32,25-36</pos>
    <because>this.code.length</because>
    <becauseType>polyglot.ast.Field_c</becauseType>
    <asString>{NV59} ==_{def} {field:length:2; NV58}@Mastermind5.jl:32,25-36</asString>
  </con>
  <con>
    <lhs>
      <label name="NV58" isvar="true" weight="1" procedure="1"/>
    </lhs>
    <rhs name="NV59" isvar="true" weight="1" procedure="1" canDecl="true"/>
    <pos>Mastermind5.jl:32,25-36</pos>
    <because>this.code.length</because>
    <becauseType>polyglot.ast.Field_c</becauseType>
    <asString>{NV59} ==_{def} {field:length:2; NV58}@Mastermind5.jl:32,25-36</asString>
  </con>
  <con>
    <lhs>
      <label name="NV59" isvar="true" weight="1" procedure="1"/>
    </lhs>
    <rhs name="NV60" isvar="true" weight="1" procedure="1" canDecl="true"/>
    <pos>Mastermind5.jl:32,21-36</pos>
    <because>i #lt this.code.length</because>
    <becauseType>jif.ast.JifBinary_c</becauseType>
    <asString>{NV60} ==_{def} {NV59; NV56}@Mastermind5.jl:32,21-36</asString>
  </con>
  <con>
    <lhs>
      <label name="NV56" isvar="true" weight="1" procedure="1"/>
    </lhs>
    <rhs name="NV60" isvar="true" weight="1" procedure="1" canDecl="true"/>
    <pos>Mastermind5.jl:32,21-36</pos>
    <because>i #lt this.code.length</because>
    <becauseType>jif.ast.JifBinary_c</becauseType>
    <asString>{NV60} ==_{def} {NV59; NV56}@Mastermind5.jl:32,21-36</asString>
  </con>
  <con>
    <lhs>
      <label name="pc55" isvar="true" weight="1" procedure="1"/>
    </lhs>
    <rhs name="pc61" isvar="true" weight="1" procedure="1"/>
    <pos>Mastermind5.jl:32,6-37</pos>
    <because>aliceGuess</because>
    <becauseType>polyglot.ast.Local_c</becauseType>
    <asString>{pc61} ==_{def} {pc55; NV60}@Mastermind5.jl:32,6-37</asString>
  </con>
  <con>
    <lhs>
      <label name="NV60" isvar="true" weight="1" procedure="1"/>
    </lhs>
    <rhs name="pc61" isvar="true" weight="1" procedure="1"/>
    <pos>Mastermind5.jl:32,6-37</pos>
    <because>aliceGuess</because>
    <becauseType>polyglot.ast.Local_c</becauseType>
    <asString>{pc61} ==_{def} {pc55; NV60}@Mastermind5.jl:32,6-37</asString>
  </con>
  <con>
    <lhs>
      <label name="LATTICE#1" isvar="false"/>
    </lhs>
    <rhs name="NV62" isvar="true" weight="1" procedure="1" canDecl="true"/>
    <pos>Mastermind5.jl:33,7-17</pos>
    <because>aliceGuess</because>
    <becauseType>polyglot.ast.Local_c</becauseType>
    <asString>{NV62} ==_{def} {Alice: }@Mastermind5.jl:33,7-17</asString>
  </con>
  <con>
    <lhs>
      <label name="local:i" isvar="true" weight="1" procedure="1"/>
    </lhs>
    <rhs name="NV63" isvar="true" weight="1" procedure="1" canDecl="true"/>
    <pos>Mastermind5.jl:33,18-19</pos>
    <because>i</because>
    <becauseType>polyglot.ast.Local_c</becauseType>
    <asString>{NV63} ==_{def} {local:i}@Mastermind5.jl:33,18-19</asString>
  </con>
  <con>
    <lhs>
      <label name="NV63" isvar="true" weight="1" procedure="1"/>
    </lhs>
    <rhs name="NV64" isvar="true" weight="1" procedure="1" canDecl="true"/>
    <pos>Mastermind5.jl:33,7-17</pos>
    <because>aliceGuess[i]</because>
    <becauseType>polyglot.ast.ArrayAccess_c</becauseType>
    <asString>{NV64} ==_{def} {NV63; NV62}@Mastermind5.jl:33,7-17</asString>
  </con>
  <con>
    <lhs>
      <label name="NV62" isvar="true" weight="1" procedure="1"/>
    </lhs>
    <rhs name="NV64" isvar="true" weight="1" procedure="1" canDecl="true"/>
    <pos>Mastermind5.jl:33,7-17</pos>
    <because>aliceGuess[i]</because>
    <becauseType>polyglot.ast.ArrayAccess_c</becauseType>
    <asString>{NV64} ==_{def} {NV63; NV62}@Mastermind5.jl:33,7-17</asString>
  </con>
  <con>
    <lhs>
      <label name="LATTICE#1" isvar="false"/>
    </lhs>
    <rhs name="NV65" isvar="true" weight="1" procedure="1" canDecl="true"/>
    <pos>Mastermind5.jl:33,7-17</pos>
    <because>aliceGuess[i]</because>
    <becauseType>polyglot.ast.ArrayAccess_c</becauseType>
    <asString>{NV65} ==_{def} {Alice: ; _!: _; NV64}@Mastermind5.jl:33,7-17</asString>
  </con>
  <con>
    <lhs>
      <label name="NV64" isvar="true" weight="1" procedure="1"/>
    </lhs>
    <rhs name="NV65" isvar="true" weight="1" procedure="1" canDecl="true"/>
    <pos>Mastermind5.jl:33,7-17</pos>
    <because>aliceGuess[i]</because>
    <becauseType>polyglot.ast.ArrayAccess_c</becauseType>
    <asString>{NV65} ==_{def} {Alice: ; _!: _; NV64}@Mastermind5.jl:33,7-17</asString>
  </con>
  <con>
    <lhs>
      <label name="guess_apireceiver" isvar="true" weight="1" procedure="-1"/>
    </lhs>
    <rhs name="NV66" isvar="true" weight="1" procedure="1" canDecl="false"/>
    <pos>Mastermind5.jl:33,24-24</pos>
    <because>this</because>
    <becauseType>polyglot.ast.Special_c</becauseType>
    <asString>{NV66} ==_{def} {guess_apireceiver; pc61}@Mastermind5.jl:33,24-24</asString>
  </con>
  <con>
    <lhs>
      <label name="pc61" isvar="true" weight="1" procedure="1"/>
    </lhs>
    <rhs name="NV66" isvar="true" weight="1" procedure="1" canDecl="false"/>
    <pos>Mastermind5.jl:33,24-24</pos>
    <because>this</because>
    <becauseType>polyglot.ast.Special_c</becauseType>
    <asString>{NV66} ==_{def} {guess_apireceiver; pc61}@Mastermind5.jl:33,24-24</asString>
  </con>
  <con>
    <lhs>
      <label name="LATTICE#2" isvar="false"/>
    </lhs>
    <rhs name="field:code" isvar="true" weight="1" procedure="-1"/>
    <pos>Mastermind5.jl:33,24-28</pos>
    <because>this.code</because>
    <becauseType>polyglot.ast.Field_c</becauseType>
    <asString>{field:code} ==_{def} {Bob: }@Mastermind5.jl:33,24-28</asString>
  </con>
  <con>
    <lhs>
      <label name="field:code" isvar="true" weight="1" procedure="-1"/>
    </lhs>
    <rhs name="NV67" isvar="true" weight="1" procedure="1" canDecl="true"/>
    <pos>Mastermind5.jl:33,24-28</pos>
    <because>this.code</because>
    <becauseType>polyglot.ast.Field_c</becauseType>
    <asString>{NV67} ==_{def} {field:code; NV66}@Mastermind5.jl:33,24-28</asString>
  </con>
  <con>
    <lhs>
      <label name="NV66" isvar="true" weight="1" procedure="1"/>
    </lhs>
    <rhs name="NV67" isvar="true" weight="1" procedure="1" canDecl="true"/>
    <pos>Mastermind5.jl:33,24-28</pos>
    <because>this.code</because>
    <becauseType>polyglot.ast.Field_c</becauseType>
    <asString>{NV67} ==_{def} {field:code; NV66}@Mastermind5.jl:33,24-28</asString>
  </con>
  <con>
    <lhs>
      <label name="local:j" isvar="true" weight="1" procedure="1"/>
    </lhs>
    <rhs name="NV68" isvar="true" weight="1" procedure="1" canDecl="true"/>
    <pos>Mastermind5.jl:33,29-30</pos>
    <because>j</because>
    <becauseType>polyglot.ast.Local_c</becauseType>
    <asString>{NV68} ==_{def} {local:j}@Mastermind5.jl:33,29-30</asString>
  </con>
  <con>
    <lhs>
      <label name="NV68" isvar="true" weight="1" procedure="1"/>
    </lhs>
    <rhs name="NV69" isvar="true" weight="1" procedure="1" canDecl="true"/>
    <pos>Mastermind5.jl:33,24-28</pos>
    <because>this.code[j]</because>
    <becauseType>polyglot.ast.ArrayAccess_c</becauseType>
    <asString>{NV69} ==_{def} {NV68; NV67}@Mastermind5.jl:33,24-28</asString>
  </con>
  <con>
    <lhs>
      <label name="NV67" isvar="true" weight="1" procedure="1"/>
    </lhs>
    <rhs name="NV69" isvar="true" weight="1" procedure="1" canDecl="true"/>
    <pos>Mastermind5.jl:33,24-28</pos>
    <because>this.code[j]</because>
    <becauseType>polyglot.ast.ArrayAccess_c</becauseType>
    <asString>{NV69} ==_{def} {NV68; NV67}@Mastermind5.jl:33,24-28</asString>
  </con>
  <con>
    <lhs>
      <label name="LATTICE#2" isvar="false"/>
    </lhs>
    <rhs name="NV70" isvar="true" weight="1" procedure="1" canDecl="true"/>
    <pos>Mastermind5.jl:33,24-28</pos>
    <because>this.code[j]</because>
    <becauseType>polyglot.ast.ArrayAccess_c</becauseType>
    <asString>{NV70} ==_{def} {Bob: ; _!: _; NV69}@Mastermind5.jl:33,24-28</asString>
  </con>
  <con>
    <lhs>
      <label name="NV69" isvar="true" weight="1" procedure="1"/>
    </lhs>
    <rhs name="NV70" isvar="true" weight="1" procedure="1" canDecl="true"/>
    <pos>Mastermind5.jl:33,24-28</pos>
    <because>this.code[j]</because>
    <becauseType>polyglot.ast.ArrayAccess_c</becauseType>
    <asString>{NV70} ==_{def} {Bob: ; _!: _; NV69}@Mastermind5.jl:33,24-28</asString>
  </con>
  <con>
    <lhs>
      <label name="NV70" isvar="true" weight="1" procedure="1"/>
    </lhs>
    <rhs name="NV71" isvar="true" weight="1" procedure="1" canDecl="true"/>
    <pos>Mastermind5.jl:33,7-28</pos>
    <because>aliceGuess[i] == this.code[j]</because>
    <becauseType>jif.ast.JifBinary_c</becauseType>
    <asString>{NV71} ==_{def} {NV70; NV65}@Mastermind5.jl:33,7-28</asString>
  </con>
  <con>
    <lhs>
      <label name="NV65" isvar="true" weight="1" procedure="1"/>
    </lhs>
    <rhs name="NV71" isvar="true" weight="1" procedure="1" canDecl="true"/>
    <pos>Mastermind5.jl:33,7-28</pos>
    <because>aliceGuess[i] == this.code[j]</because>
    <becauseType>jif.ast.JifBinary_c</becauseType>
    <asString>{NV71} ==_{def} {NV70; NV65}@Mastermind5.jl:33,7-28</asString>
  </con>
  <con>
    <lhs>
      <label name="pc61" isvar="true" weight="1" procedure="1"/>
    </lhs>
    <rhs name="pc72" isvar="true" weight="1" procedure="1"/>
    <pos>Mastermind5.jl:33,7-34:41</pos>
    <because>usedToIndicateCorrectColor</because>
    <becauseType>polyglot.ast.Local_c</becauseType>
    <asString>{pc72} ==_{def} {pc61; NV71}@Mastermind5.jl:33,7-34:41</asString>
  </con>
  <con>
    <lhs>
      <label name="NV71" isvar="true" weight="1" procedure="1"/>
    </lhs>
    <rhs name="pc72" isvar="true" weight="1" procedure="1"/>
    <pos>Mastermind5.jl:33,7-34:41</pos>
    <because>usedToIndicateCorrectColor</because>
    <becauseType>polyglot.ast.Local_c</becauseType>
    <asString>{pc72} ==_{def} {pc61; NV71}@Mastermind5.jl:33,7-34:41</asString>
  </con>
  <con>
    <lhs>
      <label name="local:usedToIndicateCorrectColor" isvar="true" weight="1" procedure="1"/>
    </lhs>
    <rhs name="NV73" isvar="true" weight="1" procedure="1" canDecl="true"/>
    <pos>Mastermind5.jl:34,7-33</pos>
    <because>usedToIndicateCorrectColor</because>
    <becauseType>polyglot.ast.Local_c</becauseType>
    <asString>{NV73} ==_{def} {local:usedToIndicateCorrectColor}@Mastermind5.jl:34,7-33</asString>
  </con>
  <con>
    <lhs>
      <label name="local:i" isvar="true" weight="1" procedure="1"/>
    </lhs>
    <rhs name="NV74" isvar="true" weight="1" procedure="1" canDecl="true"/>
    <pos>Mastermind5.jl:34,34-35</pos>
    <because>i</because>
    <becauseType>polyglot.ast.Local_c</becauseType>
    <asString>{NV74} ==_{def} {local:i}@Mastermind5.jl:34,34-35</asString>
  </con>
  <con>
    <lhs>
      <label name="NV74" isvar="true" weight="1" procedure="1"/>
    </lhs>
    <rhs name="NV75" isvar="true" weight="1" procedure="1" canDecl="true"/>
    <pos>Mastermind5.jl:34,7-33</pos>
    <because>usedToIndicateCorrectColor[i]</because>
    <becauseType>polyglot.ast.ArrayAccess_c</becauseType>
    <asString>{NV75} ==_{def} {NV74; NV73}@Mastermind5.jl:34,7-33</asString>
  </con>
  <con>
    <lhs>
      <label name="NV73" isvar="true" weight="1" procedure="1"/>
    </lhs>
    <rhs name="NV75" isvar="true" weight="1" procedure="1" canDecl="true"/>
    <pos>Mastermind5.jl:34,7-33</pos>
    <because>usedToIndicateCorrectColor[i]</because>
    <becauseType>polyglot.ast.ArrayAccess_c</becauseType>
    <asString>{NV75} ==_{def} {NV74; NV73}@Mastermind5.jl:34,7-33</asString>
  </con>
  <con>
    <lhs>
      <label name="NV6" isvar="true" weight="1" procedure="1"/>
    </lhs>
    <rhs name="NV76" isvar="true" weight="1" procedure="1" canDecl="true"/>
    <pos>Mastermind5.jl:34,7-33</pos>
    <because>usedToIndicateCorrectColor[i]</because>
    <becauseType>polyglot.ast.ArrayAccess_c</becauseType>
    <asString>{NV76} ==_{def} {NV6; NV75}@Mastermind5.jl:34,7-33</asString>
  </con>
  <con>
    <lhs>
      <label name="NV75" isvar="true" weight="1" procedure="1"/>
    </lhs>
    <rhs name="NV76" isvar="true" weight="1" procedure="1" canDecl="true"/>
    <pos>Mastermind5.jl:34,7-33</pos>
    <because>usedToIndicateCorrectColor[i]</because>
    <becauseType>polyglot.ast.ArrayAccess_c</becauseType>
    <asString>{NV76} ==_{def} {NV6; NV75}@Mastermind5.jl:34,7-33</asString>
  </con>
  <con>
    <lhs>
      <label name="LATTICE#0" isvar="false"/>
    </lhs>
    <rhs name="NV77" isvar="true" weight="1" procedure="1" canDecl="true"/>
    <pos>Mastermind5.jl:34,40-41</pos>
    <because>1</because>
    <becauseType>polyglot.ast.IntLit_c</becauseType>
    <asString>{NV77} ==_{def} {*!: }@Mastermind5.jl:34,40-41</asString>
  </con>
  <con>
    <lhs>
      <label name="NV77" isvar="true" weight="1" procedure="1"/>
    </lhs>
    <rhs name="NV78" isvar="true" weight="1" procedure="1" canDecl="true"/>
    <pos>Mastermind5.jl:34,7-41</pos>
    <because>usedToIndicateCorrectColor[i] != 1</because>
    <becauseType>jif.ast.JifBinary_c</becauseType>
    <asString>{NV78} ==_{def} {NV77; NV76}@Mastermind5.jl:34,7-41</asString>
  </con>
  <con>
    <lhs>
      <label name="NV76" isvar="true" weight="1" procedure="1"/>
    </lhs>
    <rhs name="NV78" isvar="true" weight="1" procedure="1" canDecl="true"/>
    <pos>Mastermind5.jl:34,7-41</pos>
    <because>usedToIndicateCorrectColor[i] != 1</because>
    <becauseType>jif.ast.JifBinary_c</becauseType>
    <asString>{NV78} ==_{def} {NV77; NV76}@Mastermind5.jl:34,7-41</asString>
  </con>
  <con>
    <lhs>
      <label name="NV78" isvar="true" weight="1" procedure="1"/>
    </lhs>
    <rhs name="NV79" isvar="true" weight="1" procedure="1" canDecl="true"/>
    <pos>Mastermind5.jl:33,7-34:41</pos>
    <because>aliceGuess[i] == this.code[j] #amp#amp usedToIndicateCorrectColor[i] != 1</because>
    <becauseType>jif.ast.JifBinary_c</becauseType>
    <asString>{NV79} ==_{def} {NV78; NV71}@Mastermind5.jl:33,7-34:41</asString>
  </con>
  <con>
    <lhs>
      <label name="NV71" isvar="true" weight="1" procedure="1"/>
    </lhs>
    <rhs name="NV79" isvar="true" weight="1" procedure="1" canDecl="true"/>
    <pos>Mastermind5.jl:33,7-34:41</pos>
    <because>aliceGuess[i] == this.code[j] #amp#amp usedToIndicateCorrectColor[i] != 1</because>
    <becauseType>jif.ast.JifBinary_c</becauseType>
    <asString>{NV79} ==_{def} {NV78; NV71}@Mastermind5.jl:33,7-34:41</asString>
  </con>
  <con>
    <lhs>
      <label name="pc61" isvar="true" weight="1" procedure="1"/>
    </lhs>
    <rhs name="pc80" isvar="true" weight="1" procedure="1"/>
    <pos>Mastermind5.jl:33,3-37:4</pos>
    <because>usedToIndicateCorrectColor</because>
    <becauseType>polyglot.ast.Local_c</becauseType>
    <asString>{pc80} ==_{def} {pc61; NV79}@Mastermind5.jl:33,3-37:4</asString>
  </con>
  <con>
    <lhs>
      <label name="NV79" isvar="true" weight="1" procedure="1"/>
    </lhs>
    <rhs name="pc80" isvar="true" weight="1" procedure="1"/>
    <pos>Mastermind5.jl:33,3-37:4</pos>
    <because>usedToIndicateCorrectColor</because>
    <becauseType>polyglot.ast.Local_c</becauseType>
    <asString>{pc80} ==_{def} {pc61; NV79}@Mastermind5.jl:33,3-37:4</asString>
  </con>
  <con>
    <lhs>
      <label name="local:usedToIndicateCorrectColor" isvar="true" weight="1" procedure="1"/>
    </lhs>
    <rhs name="NV81" isvar="true" weight="1" procedure="1" canDecl="true"/>
    <pos>Mastermind5.jl:35,7-33</pos>
    <because>usedToIndicateCorrectColor</because>
    <becauseType>polyglot.ast.Local_c</becauseType>
    <asString>{NV81} ==_{def} {local:usedToIndicateCorrectColor}@Mastermind5.jl:35,7-33</asString>
  </con>
  <con>
    <lhs>
      <label name="local:i" isvar="true" weight="1" procedure="1"/>
    </lhs>
    <rhs name="NV82" isvar="true" weight="1" procedure="1" canDecl="true"/>
    <pos>Mastermind5.jl:35,34-35</pos>
    <because>i</because>
    <becauseType>polyglot.ast.Local_c</becauseType>
    <asString>{NV82} ==_{def} {local:i}@Mastermind5.jl:35,34-35</asString>
  </con>
  <con>
    <lhs>
      <label name="NV82" isvar="true" weight="1" procedure="1"/>
    </lhs>
    <rhs name="NV83" isvar="true" weight="1" procedure="1" canDecl="true"/>
    <pos>Mastermind5.jl:35,7-40</pos>
    <because>1</because>
    <becauseType>polyglot.ast.IntLit_c</becauseType>
    <asString>{NV83} ==_{def} {NV82; NV81}@Mastermind5.jl:35,7-40</asString>
  </con>
  <con>
    <lhs>
      <label name="NV81" isvar="true" weight="1" procedure="1"/>
    </lhs>
    <rhs name="NV83" isvar="true" weight="1" procedure="1" canDecl="true"/>
    <pos>Mastermind5.jl:35,7-40</pos>
    <because>1</because>
    <becauseType>polyglot.ast.IntLit_c</becauseType>
    <asString>{NV83} ==_{def} {NV82; NV81}@Mastermind5.jl:35,7-40</asString>
  </con>
  <con>
    <lhs>
      <label name="LATTICE#0" isvar="false"/>
    </lhs>
    <rhs name="NV84" isvar="true" weight="1" procedure="1" canDecl="true"/>
    <pos>Mastermind5.jl:35,39-40</pos>
    <because>1</because>
    <becauseType>polyglot.ast.IntLit_c</becauseType>
    <asString>{NV84} ==_{def} {*!: }@Mastermind5.jl:35,39-40</asString>
  </con>
  <con>
    <lhs>
      <label name="NV84" isvar="true" weight="1" procedure="1"/>
    </lhs>
    <rhs name="NV85" isvar="true" weight="1" procedure="1" canDecl="true"/>
    <pos>Mastermind5.jl:35,7-40</pos>
    <because>usedToIndicateCorrectColor[i] = 1</because>
    <becauseType>jif.ast.JifArrayAccessAssign_c</becauseType>
    <asString>{NV85} ==_{def} {NV84; NV83}@Mastermind5.jl:35,7-40</asString>
  </con>
  <con>
    <lhs>
      <label name="NV83" isvar="true" weight="1" procedure="1"/>
    </lhs>
    <rhs name="NV85" isvar="true" weight="1" procedure="1" canDecl="true"/>
    <pos>Mastermind5.jl:35,7-40</pos>
    <because>usedToIndicateCorrectColor[i] = 1</because>
    <becauseType>jif.ast.JifArrayAccessAssign_c</becauseType>
    <asString>{NV85} ==_{def} {NV84; NV83}@Mastermind5.jl:35,7-40</asString>
  </con>
  <con>
    <lhs>
      <label name="NV84" isvar="true" weight="1" procedure="1"/>
    </lhs>
    <rhs name="NV6" isvar="true" weight="1" procedure="1"/>
    <pos>Mastermind5.jl:35,7-33</pos>
    <because>usedToIndicateCorrectColor[i] = 1</because>
    <becauseType>jif.ast.JifArrayAccessAssign_c</becauseType>
    <asString>{NV84; pc80} #lt= {NV6}@Mastermind5.jl:35,7-33</asString>
  </con>
  <con>
    <lhs>
      <label name="pc80" isvar="true" weight="1" procedure="1"/>
    </lhs>
    <rhs name="NV6" isvar="true" weight="1" procedure="1"/>
    <pos>Mastermind5.jl:35,7-33</pos>
    <because>usedToIndicateCorrectColor[i] = 1</because>
    <becauseType>jif.ast.JifArrayAccessAssign_c</becauseType>
    <asString>{NV84; pc80} #lt= {NV6}@Mastermind5.jl:35,7-33</asString>
  </con>
  <con>
    <lhs>
      <label name="pc80" isvar="true" weight="1" procedure="1"/>
    </lhs>
    <rhs name="NV6" isvar="true" weight="1" procedure="1"/>
    <pos>Mastermind5.jl:35,7-33</pos>
    <because>usedToIndicateCorrectColor[i] = 1</because>
    <becauseType>jif.ast.JifArrayAccessAssign_c</becauseType>
    <asString>{pc80} #lt= {NV6}@Mastermind5.jl:35,7-33</asString>
  </con>
  <con>
    <lhs>
      <label name="LATTICE#0" isvar="false"/>
    </lhs>
    <rhs name="NV6" isvar="true" weight="1" procedure="1"/>
    <pos>Mastermind5.jl:35,7-33</pos>
    <because>usedToIndicateCorrectColor[i] = 1</because>
    <becauseType>jif.ast.JifArrayAccessAssign_c</becauseType>
    <asString>{} #lt= {NV6}@Mastermind5.jl:35,7-33</asString>
  </con>
  <con>
    <lhs>
      <label name="guess_apireceiver" isvar="true" weight="1" procedure="-1"/>
    </lhs>
    <rhs name="NV86" isvar="true" weight="1" procedure="1" canDecl="false"/>
    <pos>Mastermind5.jl:36,21-21</pos>
    <because>this</because>
    <becauseType>polyglot.ast.Special_c</becauseType>
    <asString>{NV86} ==_{def} {guess_apireceiver; pc80}@Mastermind5.jl:36,21-21</asString>
  </con>
  <con>
    <lhs>
      <label name="pc80" isvar="true" weight="1" procedure="1"/>
    </lhs>
    <rhs name="NV86" isvar="true" weight="1" procedure="1" canDecl="false"/>
    <pos>Mastermind5.jl:36,21-21</pos>
    <because>this</because>
    <becauseType>polyglot.ast.Special_c</becauseType>
    <asString>{NV86} ==_{def} {guess_apireceiver; pc80}@Mastermind5.jl:36,21-21</asString>
  </con>
  <con>
    <lhs>
      <label name="inst(CORRECT_COLOR)" isvar="true" weight="1" procedure="-1"/>
    </lhs>
    <rhs name="field:CORRECT_COLOR" isvar="true" weight="1" procedure="-1"/>
    <pos>Mastermind5.jl:36,21-34</pos>
    <because>this.CORRECT_COLOR</because>
    <becauseType>polyglot.ast.Field_c</becauseType>
    <asString>{field:CORRECT_COLOR} ==_{def} {inst(CORRECT_COLOR)}@Mastermind5.jl:36,21-34</asString>
  </con>
  <con>
    <lhs>
      <label name="field:CORRECT_COLOR" isvar="true" weight="1" procedure="-1"/>
    </lhs>
    <rhs name="NV87" isvar="true" weight="1" procedure="1" canDecl="true"/>
    <pos>Mastermind5.jl:36,21-34</pos>
    <because>this.CORRECT_COLOR</because>
    <becauseType>polyglot.ast.Field_c</becauseType>
    <asString>{NV87} ==_{def} {field:CORRECT_COLOR; NV86}@Mastermind5.jl:36,21-34</asString>
  </con>
  <con>
    <lhs>
      <label name="NV86" isvar="true" weight="1" procedure="1"/>
    </lhs>
    <rhs name="NV87" isvar="true" weight="1" procedure="1" canDecl="true"/>
    <pos>Mastermind5.jl:36,21-34</pos>
    <because>this.CORRECT_COLOR</because>
    <becauseType>polyglot.ast.Field_c</becauseType>
    <asString>{NV87} ==_{def} {field:CORRECT_COLOR; NV86}@Mastermind5.jl:36,21-34</asString>
  </con>
  <con>
    <lhs>
      <label name="NV87" isvar="true" weight="1" procedure="1"/>
    </lhs>
    <rhs name="local:guessResult" isvar="true" weight="1" procedure="1"/>
    <pos>Mastermind5.jl:36,7-18</pos>
    <because>guessResult = this.CORRECT_COLOR</because>
    <becauseType>polyglot.ast.LocalAssign_c</becauseType>
    <asString>{NV87} #lt= {local:guessResult}@Mastermind5.jl:36,7-18</asString>
  </con>
  <con>
    <lhs>
      <label name="pc80" isvar="true" weight="1" procedure="1"/>
    </lhs>
    <rhs name="local:guessResult" isvar="true" weight="1" procedure="1"/>
    <pos>Mastermind5.jl:36,7-18</pos>
    <because>guessResult = this.CORRECT_COLOR</because>
    <becauseType>polyglot.ast.LocalAssign_c</becauseType>
    <asString>{pc80} #lt= {local:guessResult}@Mastermind5.jl:36,7-18</asString>
  </con>
  <con>
    <lhs>
      <label name="local:i" isvar="true" weight="1" procedure="1"/>
    </lhs>
    <rhs name="NV88" isvar="true" weight="1" procedure="1" canDecl="true"/>
    <pos>Mastermind5.jl:32,38-41</pos>
    <because>++i</because>
    <becauseType>polyglot.ast.Unary_c</becauseType>
    <asString>{NV88} ==_{def} {local:i}@Mastermind5.jl:32,38-41</asString>
  </con>
  <con>
    <lhs>
      <label name="pc61" isvar="true" weight="1" procedure="1"/>
    </lhs>
    <rhs name="local:i" isvar="true" weight="1" procedure="1"/>
    <pos>Mastermind5.jl:32,40-41</pos>
    <because>++i</because>
    <becauseType>polyglot.ast.Unary_c</becauseType>
    <asString>{pc61} #lt= {local:i}@Mastermind5.jl:32,40-41</asString>
  </con>
  <con>
    <lhs>
      <label name="pc61" isvar="true" weight="1" procedure="1"/>
    </lhs>
    <rhs name="for:2" isvar="true" weight="1" procedure="1"/>
    <pos>Mastermind5.jl:32,6-37</pos>
    <because>for (...) ...</because>
    <becauseType>polyglot.ast.For_c</becauseType>
    <asString>{pc61; pc52} #lt= {for:2}@Mastermind5.jl:32,6-37</asString>
  </con>
  <con>
    <lhs>
      <label name="pc52" isvar="true" weight="1" procedure="1"/>
    </lhs>
    <rhs name="for:2" isvar="true" weight="1" procedure="1"/>
    <pos>Mastermind5.jl:32,6-37</pos>
    <because>for (...) ...</because>
    <becauseType>polyglot.ast.For_c</becauseType>
    <asString>{pc61; pc52} #lt= {for:2}@Mastermind5.jl:32,6-37</asString>
  </con>
  <con>
    <lhs>
      <label name="NV60" isvar="true" weight="1" procedure="1"/>
    </lhs>
    <rhs name="NV89" isvar="true" weight="1" procedure="1" canDecl="true"/>
    <pos>Mastermind5.jl:32,6-37</pos>
    <because>for (...) ...</because>
    <becauseType>polyglot.ast.For_c</becauseType>
    <asString>{NV89} ==_{def} {NV60}@Mastermind5.jl:32,6-37</asString>
  </con>
  <con>
    <lhs>
      <label name="local:guessResult" isvar="true" weight="1" procedure="1"/>
    </lhs>
    <rhs name="NV90" isvar="true" weight="1" procedure="1" canDecl="true"/>
    <pos>Mastermind5.jl:40,6-17</pos>
    <because>guessResult</because>
    <becauseType>polyglot.ast.Local_c</becauseType>
    <asString>{NV90} ==_{def} {local:guessResult}@Mastermind5.jl:40,6-17</asString>
  </con>
  <con>
    <lhs>
      <label name="LATTICE#0" isvar="false"/>
    </lhs>
    <rhs name="NV91" isvar="true" weight="1" procedure="1" canDecl="true"/>
    <pos>Mastermind5.jl:40,22-23</pos>
    <because>1</because>
    <becauseType>polyglot.ast.IntLit_c</becauseType>
    <asString>{NV91} ==_{def} {*!: }@Mastermind5.jl:40,22-23</asString>
  </con>
  <con>
    <lhs>
      <label name="NV91" isvar="true" weight="1" procedure="1"/>
    </lhs>
    <rhs name="NV92" isvar="true" weight="1" procedure="1" canDecl="true"/>
    <pos>Mastermind5.jl:40,6-23</pos>
    <because>guessResult != -1</because>
    <becauseType>jif.ast.JifBinary_c</becauseType>
    <asString>{NV92} ==_{def} {NV91; NV90}@Mastermind5.jl:40,6-23</asString>
  </con>
  <con>
    <lhs>
      <label name="NV90" isvar="true" weight="1" procedure="1"/>
    </lhs>
    <rhs name="NV92" isvar="true" weight="1" procedure="1" canDecl="true"/>
    <pos>Mastermind5.jl:40,6-23</pos>
    <because>guessResult != -1</because>
    <becauseType>jif.ast.JifBinary_c</becauseType>
    <asString>{NV92} ==_{def} {NV91; NV90}@Mastermind5.jl:40,6-23</asString>
  </con>
  <con>
    <lhs>
      <label name="pc31" isvar="true" weight="1" procedure="1"/>
    </lhs>
    <rhs name="pc93" isvar="true" weight="1" procedure="1"/>
    <pos>Mastermind5.jl:40,2-43:3</pos>
    <because>returnArray</because>
    <becauseType>polyglot.ast.Local_c</becauseType>
    <asString>{pc93} ==_{def} {pc31; NV92}@Mastermind5.jl:40,2-43:3</asString>
  </con>
  <con>
    <lhs>
      <label name="NV92" isvar="true" weight="1" procedure="1"/>
    </lhs>
    <rhs name="pc93" isvar="true" weight="1" procedure="1"/>
    <pos>Mastermind5.jl:40,2-43:3</pos>
    <because>returnArray</because>
    <becauseType>polyglot.ast.Local_c</becauseType>
    <asString>{pc93} ==_{def} {pc31; NV92}@Mastermind5.jl:40,2-43:3</asString>
  </con>
  <con>
    <lhs>
      <label name="local:returnArray" isvar="true" weight="1" procedure="1"/>
    </lhs>
    <rhs name="NV94" isvar="true" weight="1" procedure="1" canDecl="true"/>
    <pos>Mastermind5.jl:41,6-17</pos>
    <because>returnArray</because>
    <becauseType>polyglot.ast.Local_c</becauseType>
    <asString>{NV94} ==_{def} {local:returnArray}@Mastermind5.jl:41,6-17</asString>
  </con>
  <con>
    <lhs>
      <label name="local:k" isvar="true" weight="1" procedure="1"/>
    </lhs>
    <rhs name="NV95" isvar="true" weight="1" procedure="1" canDecl="true"/>
    <pos>Mastermind5.jl:41,18-19</pos>
    <because>k</because>
    <becauseType>polyglot.ast.Local_c</becauseType>
    <asString>{NV95} ==_{def} {local:k}@Mastermind5.jl:41,18-19</asString>
  </con>
  <con>
    <lhs>
      <label name="NV95" isvar="true" weight="1" procedure="1"/>
    </lhs>
    <rhs name="NV96" isvar="true" weight="1" procedure="1" canDecl="true"/>
    <pos>Mastermind5.jl:41,6-34</pos>
    <because>guessResult</because>
    <becauseType>polyglot.ast.Local_c</becauseType>
    <asString>{NV96} ==_{def} {NV95; NV94}@Mastermind5.jl:41,6-34</asString>
  </con>
  <con>
    <lhs>
      <label name="NV94" isvar="true" weight="1" procedure="1"/>
    </lhs>
    <rhs name="NV96" isvar="true" weight="1" procedure="1" canDecl="true"/>
    <pos>Mastermind5.jl:41,6-34</pos>
    <because>guessResult</because>
    <becauseType>polyglot.ast.Local_c</becauseType>
    <asString>{NV96} ==_{def} {NV95; NV94}@Mastermind5.jl:41,6-34</asString>
  </con>
  <con>
    <lhs>
      <label name="local:guessResult" isvar="true" weight="1" procedure="1"/>
    </lhs>
    <rhs name="NV97" isvar="true" weight="1" procedure="1" canDecl="true"/>
    <pos>Mastermind5.jl:41,23-34</pos>
    <because>guessResult</because>
    <becauseType>polyglot.ast.Local_c</becauseType>
    <asString>{NV97} ==_{def} {local:guessResult}@Mastermind5.jl:41,23-34</asString>
  </con>
  <con>
    <lhs>
      <label name="NV97" isvar="true" weight="1" procedure="1"/>
    </lhs>
    <rhs name="NV98" isvar="true" weight="1" procedure="1" canDecl="true"/>
    <pos>Mastermind5.jl:41,6-34</pos>
    <because>returnArray[k] = guessResult</because>
    <becauseType>jif.ast.JifArrayAccessAssign_c</becauseType>
    <asString>{NV98} ==_{def} {NV97; NV96}@Mastermind5.jl:41,6-34</asString>
  </con>
  <con>
    <lhs>
      <label name="NV96" isvar="true" weight="1" procedure="1"/>
    </lhs>
    <rhs name="NV98" isvar="true" weight="1" procedure="1" canDecl="true"/>
    <pos>Mastermind5.jl:41,6-34</pos>
    <because>returnArray[k] = guessResult</because>
    <becauseType>jif.ast.JifArrayAccessAssign_c</becauseType>
    <asString>{NV98} ==_{def} {NV97; NV96}@Mastermind5.jl:41,6-34</asString>
  </con>
  <con>
    <lhs>
      <label name="NV97" isvar="true" weight="1" procedure="1"/>
    </lhs>
    <rhs name="LATTICE#1" isvar="false"/>
    <pos>Mastermind5.jl:41,6-17</pos>
    <because>returnArray[k] = guessResult</because>
    <becauseType>jif.ast.JifArrayAccessAssign_c</becauseType>
    <asString>{NV97; pc93} #lt= {Alice: }@Mastermind5.jl:41,6-17</asString>
  </con>
  <con>
    <lhs>
      <label name="pc93" isvar="true" weight="1" procedure="1"/>
    </lhs>
    <rhs name="LATTICE#1" isvar="false"/>
    <pos>Mastermind5.jl:41,6-17</pos>
    <because>returnArray[k] = guessResult</because>
    <becauseType>jif.ast.JifArrayAccessAssign_c</becauseType>
    <asString>{NV97; pc93} #lt= {Alice: }@Mastermind5.jl:41,6-17</asString>
  </con>
  <con>
    <lhs>
      <label name="pc93" isvar="true" weight="1" procedure="1"/>
    </lhs>
    <rhs name="LATTICE#1" isvar="false"/>
    <pos>Mastermind5.jl:41,6-17</pos>
    <because>returnArray[k] = guessResult</because>
    <becauseType>jif.ast.JifArrayAccessAssign_c</becauseType>
    <asString>{pc93} #lt= {Alice: }@Mastermind5.jl:41,6-17</asString>
  </con>
  <con>
    <lhs>
      <label name="LATTICE#0" isvar="false"/>
    </lhs>
    <rhs name="LATTICE#1" isvar="false"/>
    <pos>Mastermind5.jl:41,6-17</pos>
    <because>returnArray[k] = guessResult</because>
    <becauseType>jif.ast.JifArrayAccessAssign_c</becauseType>
    <asString>{} #lt= {Alice: }@Mastermind5.jl:41,6-17</asString>
  </con>
  <con>
    <lhs>
      <label name="local:k" isvar="true" weight="1" procedure="1"/>
    </lhs>
    <rhs name="NV99" isvar="true" weight="1" procedure="1" canDecl="true"/>
    <pos>Mastermind5.jl:42,6-9</pos>
    <because>++k</because>
    <becauseType>polyglot.ast.Unary_c</becauseType>
    <asString>{NV99} ==_{def} {local:k}@Mastermind5.jl:42,6-9</asString>
  </con>
  <con>
    <lhs>
      <label name="pc93" isvar="true" weight="1" procedure="1"/>
    </lhs>
    <rhs name="local:k" isvar="true" weight="1" procedure="1"/>
    <pos>Mastermind5.jl:42,8-9</pos>
    <because>++k</because>
    <becauseType>polyglot.ast.Unary_c</becauseType>
    <asString>{pc93} #lt= {local:k}@Mastermind5.jl:42,8-9</asString>
  </con>
  <con>
    <lhs>
      <label name="local:j" isvar="true" weight="1" procedure="1"/>
    </lhs>
    <rhs name="NV100" isvar="true" weight="1" procedure="1" canDecl="true"/>
    <pos>Mastermind5.jl:24,37-40</pos>
    <because>++j</because>
    <becauseType>polyglot.ast.Unary_c</becauseType>
    <asString>{NV100} ==_{def} {local:j}@Mastermind5.jl:24,37-40</asString>
  </con>
  <con>
    <lhs>
      <label name="pc31" isvar="true" weight="1" procedure="1"/>
    </lhs>
    <rhs name="local:j" isvar="true" weight="1" procedure="1"/>
    <pos>Mastermind5.jl:24,39-40</pos>
    <because>++j</because>
    <becauseType>polyglot.ast.Unary_c</becauseType>
    <asString>{pc31} #lt= {local:j}@Mastermind5.jl:24,39-40</asString>
  </con>
  <con>
    <lhs>
      <label name="pc31" isvar="true" weight="1" procedure="1"/>
    </lhs>
    <rhs name="for" isvar="true" weight="1" procedure="1"/>
    <pos>Mastermind5.jl:24,5-36</pos>
    <because>for (...) ...</because>
    <becauseType>polyglot.ast.For_c</becauseType>
    <asString>{pc31; pc17} #lt= {for}@Mastermind5.jl:24,5-36</asString>
  </con>
  <con>
    <lhs>
      <label name="pc17" isvar="true" weight="1" procedure="1"/>
    </lhs>
    <rhs name="for" isvar="true" weight="1" procedure="1"/>
    <pos>Mastermind5.jl:24,5-36</pos>
    <because>for (...) ...</because>
    <becauseType>polyglot.ast.For_c</becauseType>
    <asString>{pc31; pc17} #lt= {for}@Mastermind5.jl:24,5-36</asString>
  </con>
  <con>
    <lhs>
      <label name="NV30" isvar="true" weight="1" procedure="1"/>
    </lhs>
    <rhs name="NV101" isvar="true" weight="1" procedure="1" canDecl="true"/>
    <pos>Mastermind5.jl:24,5-36</pos>
    <because>for (...) ...</because>
    <becauseType>polyglot.ast.For_c</becauseType>
    <asString>{NV101} ==_{def} {NV30}@Mastermind5.jl:24,5-36</asString>
  </con>
  <con>
    <lhs>
      <label name="guess_apireceiver" isvar="true" weight="1" procedure="-1"/>
    </lhs>
    <rhs name="NV102" isvar="true" weight="1" procedure="1" canDecl="false"/>
    <pos>Mastermind5.jl:45,7-7</pos>
    <because>this</because>
    <becauseType>polyglot.ast.Special_c</becauseType>
    <asString>{NV102} ==_{def} {guess_apireceiver; pc17}@Mastermind5.jl:45,7-7</asString>
  </con>
  <con>
    <lhs>
      <label name="pc17" isvar="true" weight="1" procedure="1"/>
    </lhs>
    <rhs name="NV102" isvar="true" weight="1" procedure="1" canDecl="false"/>
    <pos>Mastermind5.jl:45,7-7</pos>
    <because>this</because>
    <becauseType>polyglot.ast.Special_c</becauseType>
    <asString>{NV102} ==_{def} {guess_apireceiver; pc17}@Mastermind5.jl:45,7-7</asString>
  </con>
  <con>
    <lhs>
      <label name="LATTICE#0" isvar="false"/>
    </lhs>
    <rhs name="NV103" isvar="true" weight="1" procedure="1" canDecl="true"/>
    <pos>Mastermind5.jl:45,7-17</pos>
    <because>1</because>
    <becauseType>polyglot.ast.IntLit_c</becauseType>
    <asString>{NV103} ==_{def} {*!: }@Mastermind5.jl:45,7-17</asString>
  </con>
  <con>
    <lhs>
      <label name="NV103" isvar="true" weight="1" procedure="1"/>
    </lhs>
    <rhs name="NV104" isvar="true" weight="1" procedure="1" canDecl="true"/>
    <pos>Mastermind5.jl:45,7-17</pos>
    <because>this.numGuesses += 1</because>
    <becauseType>polyglot.ast.FieldAssign_c</becauseType>
    <asString>{NV104} ==_{def} {NV103; NV102}@Mastermind5.jl:45,7-17</asString>
  </con>
  <con>
    <lhs>
      <label name="NV102" isvar="true" weight="1" procedure="1"/>
    </lhs>
    <rhs name="NV104" isvar="true" weight="1" procedure="1" canDecl="true"/>
    <pos>Mastermind5.jl:45,7-17</pos>
    <because>this.numGuesses += 1</because>
    <becauseType>polyglot.ast.FieldAssign_c</becauseType>
    <asString>{NV104} ==_{def} {NV103; NV102}@Mastermind5.jl:45,7-17</asString>
  </con>
  <con>
    <lhs>
      <label name="NV103" isvar="true" weight="1" procedure="1"/>
    </lhs>
    <rhs name="inst(numGuesses)" isvar="true" weight="1" procedure="-1"/>
    <pos>Mastermind5.jl:45,7-17</pos>
    <because>this.numGuesses += 1</because>
    <becauseType>polyglot.ast.FieldAssign_c</becauseType>
    <asString>{NV103} #lt= {inst(numGuesses)}@Mastermind5.jl:45,7-17</asString>
  </con>
  <con>
    <lhs>
      <label name="NV102" isvar="true" weight="1" procedure="1"/>
    </lhs>
    <rhs name="inst(numGuesses)" isvar="true" weight="1" procedure="-1"/>
    <pos>Mastermind5.jl:45,7-17</pos>
    <because>this.numGuesses += 1</because>
    <becauseType>polyglot.ast.FieldAssign_c</becauseType>
    <asString>{NV102} #lt= {inst(numGuesses)}@Mastermind5.jl:45,7-17</asString>
  </con>
  <con>
    <lhs>
      <label name="pc17" isvar="true" weight="1" procedure="1"/>
    </lhs>
    <rhs name="inst(numGuesses)" isvar="true" weight="1" procedure="-1"/>
    <pos>Mastermind5.jl:45,7-17</pos>
    <because>this.numGuesses += 1</because>
    <becauseType>polyglot.ast.FieldAssign_c</becauseType>
    <asString>{pc17} #lt= {inst(numGuesses)}@Mastermind5.jl:45,7-17</asString>
  </con>
  <con>
    <lhs>
      <label name="LATTICE#0" isvar="false"/>
    </lhs>
    <rhs name="inst(numGuesses)" isvar="true" weight="1" procedure="-1"/>
    <pos>Mastermind5.jl:45,7-17</pos>
    <because>this.numGuesses += 1</because>
    <becauseType>polyglot.ast.FieldAssign_c</becauseType>
    <asString>{} #lt= {inst(numGuesses)}@Mastermind5.jl:45,7-17</asString>
  </con>
  <con>
    <lhs>
      <label name="NV104" isvar="true" weight="1" procedure="1"/>
    </lhs>
    <rhs name="NV105" isvar="true" weight="1" procedure="1" canDecl="true"/>
    <pos>Mastermind5.jl:45,7-17</pos>
    <because>this.numGuesses += 1</because>
    <becauseType>polyglot.ast.FieldAssign_c</becauseType>
    <asString>{NV105} ==_{def} {NV104; inst(numGuesses)}@Mastermind5.jl:45,7-17</asString>
  </con>
  <con>
    <lhs>
      <label name="inst(numGuesses)" isvar="true" weight="1" procedure="-1"/>
    </lhs>
    <rhs name="NV105" isvar="true" weight="1" procedure="1" canDecl="true"/>
    <pos>Mastermind5.jl:45,7-17</pos>
    <because>this.numGuesses += 1</because>
    <becauseType>polyglot.ast.FieldAssign_c</becauseType>
    <asString>{NV105} ==_{def} {NV104; inst(numGuesses)}@Mastermind5.jl:45,7-17</asString>
  </con>
  <con>
    <lhs>
      <label name="local:returnArray" isvar="true" weight="1" procedure="1"/>
    </lhs>
    <rhs name="NV106" isvar="true" weight="1" procedure="1" canDecl="true"/>
    <pos>Mastermind5.jl:48,8-19</pos>
    <because>returnArray</because>
    <becauseType>polyglot.ast.Local_c</becauseType>
    <asString>{NV106} ==_{def} {local:returnArray}@Mastermind5.jl:48,8-19</asString>
  </con>
  <con>
    <lhs>
      <label name="pc8" isvar="true" weight="1" procedure="1"/>
    </lhs>
    <rhs name="R107" isvar="true" weight="1" procedure="-1"/>
    <pos>Mastermind5.jl:48,1-20</pos>
    <because>return returnArray;</because>
    <becauseType>polyglot.ast.Return_c</becauseType>
    <asString>{R107} ==_{def} {pc8}@Mastermind5.jl:48,1-20</asString>
  </con>
  <con>
    <lhs>
      <label name="NV106" isvar="true" weight="1" procedure="1"/>
    </lhs>
    <rhs name="LATTICE#1" isvar="false"/>
    <pos>Mastermind5.jl:48,1-20</pos>
    <because>return returnArray;</because>
    <becauseType>polyglot.ast.Return_c</becauseType>
    <asString>{NV106} #lt= {Alice: }@Mastermind5.jl:48,1-20</asString>
  </con>
  <con>
    <lhs>
      <label name="pc8" isvar="true" weight="1" procedure="1"/>
    </lhs>
    <rhs name="R108" isvar="true" weight="1" procedure="-1"/>
    <pos>Mastermind5.jl:48,1-20</pos>
    <because>return returnArray;</because>
    <becauseType>polyglot.ast.Return_c</becauseType>
    <asString>{R108} ==_{def} {pc8}@Mastermind5.jl:48,1-20</asString>
  </con>
  <con>
    <lhs>
      <label name="R108" isvar="true" weight="1" procedure="-1"/>
    </lhs>
    <rhs name="R110" isvar="true" weight="1" procedure="-1"/>
    <pos>Mastermind5.jl:11,75-49:5</pos>
    <because>{ int{Alice: }[]{Alice: } returnArray = null; if (aliceGuess.length == this.code.length) { eval(returnArray = new int[...]); int{local:k} k = 0; int{NV6}[]{local:usedToIndicateCorrectColor} usedToIndicateCorrectColor; ... } return returnArray; }</because>
    <becauseType>polyglot.ast.Block_c</becauseType>
    <asString>{R110} ==_{def} {R108}@Mastermind5.jl:11,75-49:5</asString>
  </con>
  <con>
    <lhs>
      <label name="pc8" isvar="true" weight="1" procedure="1"/>
    </lhs>
    <rhs name="R111" isvar="true" weight="1" procedure="-1"/>
    <pos>Mastermind5.jl:11,75-49:5</pos>
    <because>{ int{Alice: }[]{Alice: } returnArray = null; if (aliceGuess.length == this.code.length) { eval(returnArray = new int[...]); int{local:k} k = 0; int{NV6}[]{local:usedToIndicateCorrectColor} usedToIndicateCorrectColor; ... } return returnArray; }</because>
    <becauseType>polyglot.ast.Block_c</becauseType>
    <asString>{R111} ==_{def} {pc8}@Mastermind5.jl:11,75-49:5</asString>
  </con>
  <con>
    <lhs>
      <label name="R111" isvar="true" weight="1" procedure="-1"/>
    </lhs>
    <rhs name="LATTICE#0" isvar="false"/>
    <pos>Mastermind5.jl:11,11-38</pos>
    <because>public int{Alice: }[]{Alice: } guess(...)</because>
    <becauseType>jif.ast.JifMethodDecl_c</becauseType>
    <asString>{R111} #lt= {}@Mastermind5.jl:11,11-38</asString>
  </con>
  <lattice>
    <label name="{Bob: }" id="2"/>
    <label name="{Alice: }" id="1"/>
    <label name="{*!: }" id="0"/>
    <lt lhs="0" rhs="2"/>
    <lt lhs="0" rhs="1"/>
  </lattice>
  <procedureList>
    <procedure name="constructor public public java.lang.Object()" id="0" weight="-1"/>
    <procedure name="method public int{Alice: }[]{Alice: } guess{}(int{Alice: }[]{aliceGuess}) : {*!: }" id="1" weight="-1"/>
    <procedure name="constructor public public Mastermind4()" id="2" weight="-1"/>
  </procedureList>

</constraint-set>
